HDL/fp16_fma.v
`timescale 1ns/1ps

// =============================================================================
// fp16_fma — IEEE 754 half-precision Fused Multiply-Add unit
//
// Computes: result = (a * b) + c  in FP16 (binary16) format.
// Pipeline latency: 3 cycles (matching MULT_LATENCY in pe_tile_stub.v).
//
// IEEE 754 half-precision format:
//   [15]    sign
//   [14:10] exponent (5 bits, bias = 15)
//   [9:0]   mantissa (10 bits, implicit leading 1)
//
// Fixes applied:
//   1. Pipeline: multiply results registered into stage 1 (s1_mul_*)
//   2. Underflow: signed norm_exp prevents unsigned wrap to infinity
//   3. Rounding: round-to-nearest-even with guard/round/sticky bits
//   4. Special cases: NaN, Inf, zero*Inf properly handled
// =============================================================================

module fp16_fma (
    input  wire        clk,
    input  wire        rst_n,
    input  wire [15:0] a,
    input  wire [15:0] b,
    input  wire [15:0] c,
    input  wire        valid_in,
    output reg  [15:0] result,
    output reg         valid_out
);

    localparam FP16_BIAS = 15;
    localparam FP16_ZERO = 16'h0000;
    localparam FP16_INF  = 16'h7C00;
    localparam FP16_NAN  = 16'h7E00;

    // =========================================================================
    // Pipeline stage 1: register inputs + detect special cases + multiply
    // =========================================================================
    reg [15:0] s1_a, s1_b, s1_c;
    reg        s1_valid;

    // Special case flags (registered with inputs)
    reg s1_a_nan, s1_b_nan, s1_c_nan;
    reg s1_a_inf, s1_b_inf, s1_c_inf;
    reg s1_a_zero, s1_b_zero, s1_c_zero;

    // Registered multiply results (fix #1: must travel with s1_c)
    reg [21:0] s1_mul_man;
    reg signed [7:0] s1_mul_exp;
    reg        s1_mul_sign;
    reg        s1_mul_overflow;

    // Unpack a (combinational from current inputs)
    wire        a_sign_w = a[15];
    wire [4:0]  a_exp_w  = a[14:10];
    wire [9:0]  a_man_w  = a[9:0];
    wire        a_zero_w = (a[14:0] == 15'h0000);
    wire        a_den_w  = (a_exp_w == 0) && (a_man_w != 0);

    wire [10:0] a_mantissa_w;
    assign a_mantissa_w[10]   = (a_zero_w || a_den_w) ? 1'b0 : 1'b1;
    assign a_mantissa_w[9:0]  = a_zero_w ? 10'd0 : (a_den_w ? {1'b0, a_man_w} : a_man_w);
    wire [5:0]  a_exponent_w = a_zero_w ? 6'd0 : (a_den_w ? 6'd1 : {1'b0, a_exp_w});

    // Unpack b (combinational from current inputs)
    wire        b_sign_w = b[15];
    wire [4:0]  b_exp_w  = b[14:10];
    wire [9:0]  b_man_w  = b[9:0];
    wire        b_zero_w = (b[14:0] == 15'h0000);
    wire        b_den_w  = (b_exp_w == 0) && (b_man_w != 0);

    wire [10:0] b_mantissa_w;
    assign b_mantissa_w[10]   = (b_zero_w || b_den_w) ? 1'b0 : 1'b1;
    assign b_mantissa_w[9:0]  = b_zero_w ? 10'd0 : (b_den_w ? {1'b0, b_man_w} : b_man_w);
    wire [5:0]  b_exponent_w = b_zero_w ? 6'd0 : (b_den_w ? 6'd1 : {1'b0, b_exp_w});

    // Multiply (combinational, registered next cycle)
    // Bug fix #1: force exponent and mantissa to zero when either operand
    // is zero, preventing unsigned underflow of (0 + exp - 15) which wraps
    // to 113+ in 7-bit arithmetic.
    wire        mul_sign_w = a_sign_w ^ b_sign_w;
    wire signed [7:0] mul_exp_w = (a_zero_w || b_zero_w) ? 8'sd0 :
        $signed({1'b0, a_exponent_w}) + $signed({1'b0, b_exponent_w}) - 8'sd15;
    wire [21:0] mul_man_w  = (a_zero_w || b_zero_w) ? 22'd0 :
                             (a_mantissa_w * b_mantissa_w);
    wire        mul_ovf_w  = mul_man_w[21];

    always @(posedge clk or negedge rst_n) begin
        if (!rst_n) begin
            s1_a <= 0; s1_b <= 0; s1_c <= 0;
            s1_valid <= 0;
            s1_a_nan <= 0; s1_b_nan <= 0; s1_c_nan <= 0;
            s1_a_inf <= 0; s1_b_inf <= 0; s1_c_inf <= 0;
            s1_a_zero <= 0; s1_b_zero <= 0; s1_c_zero <= 0;
            s1_mul_man <= 0; s1_mul_exp <= 0;
            s1_mul_sign <= 0; s1_mul_overflow <= 0;
        end else begin
            s1_a <= a; s1_b <= b; s1_c <= c;
            s1_valid <= valid_in;
            s1_a_nan   <= (a[14:10] == 5'd31) && (a[9:0] != 10'd0);
            s1_b_nan   <= (b[14:10] == 5'd31) && (b[9:0] != 10'd0);
            s1_c_nan   <= (c[14:10] == 5'd31) && (c[9:0] != 10'd0);
            s1_a_inf   <= (a[14:10] == 5'd31) && (a[9:0] == 10'd0);
            s1_b_inf   <= (b[14:10] == 5'd31) && (b[9:0] == 10'd0);
            s1_c_inf   <= (c[14:10] == 5'd31) && (c[9:0] == 10'd0);
            s1_a_zero  <= (a[14:0] == 15'h0000);
            s1_b_zero  <= (b[14:0] == 15'h0000);
            s1_c_zero  <= (c[14:0] == 15'h0000);
            s1_mul_man      <= mul_man_w;
            s1_mul_exp      <= mul_exp_w;
            s1_mul_sign     <= mul_sign_w;
            s1_mul_overflow <= mul_ovf_w;
        end
    end

    // =========================================================================
    // Pipeline stage 2: align, add, normalize, round, pack
    // =========================================================================

    // Unpack s1_c (the addend, from registered s1_c)
    wire        c_sign = s1_c[15];
    wire [4:0]  c_exp  = s1_c[14:10];
    wire [9:0]  c_man  = s1_c[9:0];
    wire        c_den  = (c_exp == 0) && (c_man != 0);

    wire [10:0] c_mantissa;
    assign c_mantissa[10]   = (s1_c_zero || c_den) ? 1'b0 : 1'b1;
    assign c_mantissa[9:0]  = s1_c_zero ? 10'd0 : (c_den ? {1'b0, c_man} : c_man);
    wire [5:0]  c_exponent = s1_c_zero ? 6'd0 : (c_den ? 6'd1 : {1'b0, c_exp});

    // Effective multiply exponent (from registered multiply results)
    wire signed [7:0] mul_exp_eff = s1_mul_overflow ? (s1_mul_exp + 8'sd1) : s1_mul_exp;

    // Result exponent: max(mul_exp_eff, c_exponent)
    wire signed [7:0] add_exp = (mul_exp_eff > $signed({1'b0, c_exponent})) ? mul_exp_eff : $signed({1'b0, c_exponent});
    wire signed [7:0] exp_diff = mul_exp_eff - $signed({1'b0, c_exponent});

    // Align mantissas: both have implicit 1 at bit 21
    // Bug fix #2: only shift left by 1 when product did not overflow bit 20;
    // when s1_mul_overflow=1, bit 21 is already set and <<1 would truncate it.
    wire [21:0] mul_man_norm = s1_mul_overflow ? s1_mul_man : (s1_mul_man << 1);
    wire [21:0] mul_man_aligned = (exp_diff >= 0) ?
        mul_man_norm :
        (mul_man_norm >> (-exp_diff));
    wire [21:0] c_man_aligned = (exp_diff < 0) ?
        ({c_mantissa, 11'd0}) :
        ({c_mantissa, 11'd0} >> exp_diff);

    // Add with sign/magnitude
    wire        mul_ge_c = (mul_man_aligned >= c_man_aligned);
    wire [22:0] abs_diff = mul_ge_c ?
        ({1'b0, mul_man_aligned} - {1'b0, c_man_aligned}) :
        ({1'b0, c_man_aligned} - {1'b0, mul_man_aligned});

    wire        add_sign = (s1_mul_sign == c_sign) ? s1_mul_sign :
                           mul_ge_c ? s1_mul_sign : c_sign;
    wire [22:0] add_result = (s1_mul_sign == c_sign) ?
        ({1'b0, mul_man_aligned} + {1'b0, c_man_aligned}) :
        abs_diff;

    // Normalize (fix #2: signed exponent prevents underflow wrap)
    reg [21:0] norm_man;
    reg signed [7:0] norm_exp;
    reg        norm_sign;
    reg [4:0]  lead_pos;
    integer shift;

    always @(*) begin
        norm_sign = add_sign;
        if (add_result == 0) begin
            norm_man = 0;
            norm_exp = 0;
        end else if (add_result[22]) begin
            norm_man = add_result[22:1];
            norm_exp = {1'b0, add_exp} + 8'd1;
        end else begin
            norm_man = add_result[21:0];
            norm_exp = {1'b0, add_exp};
            if (!norm_man[21]) begin
                lead_pos = 0;
                if      (norm_man[20]) lead_pos = 1;
                else if (norm_man[19]) lead_pos = 2;
                else if (norm_man[18]) lead_pos = 3;
                else if (norm_man[17]) lead_pos = 4;
                else if (norm_man[16]) lead_pos = 5;
                else if (norm_man[15]) lead_pos = 6;
                else if (norm_man[14]) lead_pos = 7;
                else if (norm_man[13]) lead_pos = 8;
                else if (norm_man[12]) lead_pos = 9;
                else if (norm_man[11]) lead_pos = 10;
                else if (norm_man[10]) lead_pos = 11;
                else if (norm_man[9])  lead_pos = 12;
                else if (norm_man[8])  lead_pos = 13;
                else if (norm_man[7])  lead_pos = 14;
                else if (norm_man[6])  lead_pos = 15;
                else if (norm_man[5])  lead_pos = 16;
                else if (norm_man[4])  lead_pos = 17;
                else if (norm_man[3])  lead_pos = 18;
                else if (norm_man[2])  lead_pos = 19;
                else if (norm_man[1])  lead_pos = 20;
                else                   lead_pos = 21;
                shift = lead_pos;
                norm_man = norm_man << shift;
                norm_exp = norm_exp - shift;
            end
        end
    end

    // Round-to-nearest-even (fix #3)
    // After normalization, implicit 1 at bit 21.
    // Mantissa field: norm_man[20:11] (10 bits)
    // Guard bit: norm_man[10], Round: norm_man[9], Sticky: |norm_man[8:0]
    wire guard  = norm_man[10];
    wire round  = norm_man[9];
    wire sticky = |norm_man[8:0];

    // Round up if: guard=1 AND (round=1 OR sticky=1 OR LSB of mantissa=1)
    wire round_up = guard & (round | sticky | norm_man[11]);

    // Apply rounding: add 1 at bit position 10 (LSB of mantissa field in norm_man)
    wire [21:0] rounded_man = norm_man + (round_up ? 22'd1024 : 22'd0);

    // Detect carry from rounding (bit 21 went from 1 to 0 = overflow)
    wire rounded_carry = ~rounded_man[21] & norm_man[21];

    // Bug fix #3: 22'h002000 was 1<<13, should be 22'h200000 (1<<21)
    wire [21:0] final_man = rounded_carry ? 22'h200000 : rounded_man;
    wire [7:0]  final_exp = rounded_carry ? (norm_exp + 8'd1) : norm_exp;

    // Pack result
    // Underflow: norm_exp < 0 (signed), or norm_exp == 0 with no rounding carry
    wire result_underflow = (norm_exp < 0) || (norm_exp == 0 && !rounded_carry);
    wire result_overflow  = (final_exp >= 31);
    wire [15:0] packed_result;
    assign packed_result = result_underflow ? (norm_sign ? 16'h8000 : FP16_ZERO) :
                           result_overflow  ? {norm_sign, 5'd31, 10'd0} :
                           {norm_sign, final_exp[4:0], final_man[20:11]};

    // =========================================================================
    // Special case handling (fix #4)
    // =========================================================================
    // NaN * anything = NaN
    // Inf * 0 = NaN
    // Inf * finite = Inf (with sign)
    // finite * Inf = Inf (with sign)
    // NaN + anything = NaN
    // Inf + anything = Inf (unless Inf + (-Inf) = NaN)
    wire any_nan = s1_a_nan | s1_b_nan | s1_c_nan;
    wire mul_inf_zero = (s1_a_inf & s1_b_zero) | (s1_b_inf & s1_a_zero);
    wire mul_inf = s1_a_inf | s1_b_inf;
    wire add_inf = s1_c_inf;

    // Check if we are doing Inf + (-Inf) for the addend (which = NaN)
    // This happens when: (a*b) produced Inf with some sign, and c is Inf with opposite sign
    wire inf_add_nan = mul_inf & add_inf & (s1_mul_sign != c_sign);

    wire is_special = any_nan | mul_inf_zero | mul_inf | add_inf;

    wire [15:0] special_result =
        any_nan      ? FP16_NAN :
        mul_inf_zero ? FP16_NAN :
        inf_add_nan  ? FP16_NAN :
        mul_inf      ? {s1_mul_sign, 5'd31, 10'd0} :
        add_inf      ? s1_c :
                       packed_result;

    reg [15:0] s2_result;
    reg        s2_valid;

    always @(posedge clk or negedge rst_n) begin
        if (!rst_n) begin
            s2_result <= 0;
            s2_valid  <= 0;
        end else begin
            s2_result <= is_special ? special_result : packed_result;
            s2_valid  <= s1_valid;
        end
    end

    // =========================================================================
    // Pipeline stage 3: output register
    // =========================================================================
    always @(posedge clk or negedge rst_n) begin
        if (!rst_n) begin
            result    <= 0;
            valid_out <= 0;
        end else begin
            result    <= s2_result;
            valid_out <= s2_valid;
        end
    end

endmodule

HDL/tb_fp16_fma.v
`timescale 1ns/1ps

// =============================================================================
// tb_fp16_fma — self-checking testbench for FP16 FMA unit
// Tests: basic ops, NaN propagation, Inf arithmetic, underflow, rounding
// =============================================================================
module tb_fp16_fma;

    reg         clk = 0;
    reg         rst_n = 0;
    reg  [15:0] a, b, c;
    reg         valid_in;
    wire [15:0] result;
    wire        valid_out;

    always #5 clk = ~clk;

    fp16_fma dut (
        .clk(clk), .rst_n(rst_n),
        .a(a), .b(b), .c(c), .valid_in(valid_in),
        .result(result), .valid_out(valid_out)
    );

    integer errors;

    task check;
        input [15:0] exp;
        input [8*32-1:0] name;
        begin
            if (result !== exp) begin
                $display("[TB] MISMATCH (%0s): a=%h b=%h c=%h -> got %h, expected %h", name, a, b, c, result, exp);
                errors = errors + 1;
            end
        end
    endtask

    task run_op;
        begin
            valid_in = 1; #10; valid_in = 0;
            repeat (4) @(posedge clk);
        end
    endtask

    initial begin
        $dumpfile("tb_fp16_fma.vcd");
        $dumpvars(0, tb_fp16_fma);
        errors = 0;

        // Reset
        #25; rst_n = 1; #10;

        // --- Basic operations ---

        // Test 1: 1.0 * 1.0 + 0.0 = 1.0
        a = 16'h3C00; b = 16'h3C00; c = 16'h0000;
        run_op; check(16'h3C00, "1*1+0");

        // Test 2: 2.0 * 3.0 + 1.0 = 7.0
        a = 16'h4000; b = 16'h4200; c = 16'h3C00;
        run_op; check(16'h4700, "2*3+1");

        // Test 3: 0.5 * 0.5 + 0.0 = 0.25
        a = 16'h3800; b = 16'h3800; c = 16'h0000;
        run_op; check(16'h3400, "0.5*0.5+0");

        // Test 4: 1.0 * 0.0 + 0.0 = 0.0
        a = 16'h3C00; b = 16'h0000; c = 16'h0000;
        run_op; check(16'h0000, "1*0+0");

        // Test 5: -1.0 * 2.0 + 3.0 = 1.0
        a = 16'hBC00; b = 16'h4000; c = 16'h4200;
        run_op; check(16'h3C00, "-1*2+3");

        // --- NaN tests ---

        // Test 6: NaN * anything = NaN
        a = 16'h7E00; b = 16'h3C00; c = 16'h0000;
        run_op; check(16'h7E00, "NaN*1+0");

        // Test 7: anything * NaN = NaN
        a = 16'h3C00; b = 16'h7E00; c = 16'h0000;
        run_op; check(16'h7E00, "1*NaN+0");

        // Test 8: NaN + NaN = NaN
        a = 16'h7E00; b = 16'h3C00; c = 16'h7E00;
        run_op; check(16'h7E00, "NaN*1+NaN");

        // --- Infinity tests ---

        // Test 9: Inf * 1 + 0 = Inf
        a = 16'h7C00; b = 16'h3C00; c = 16'h0000;
        run_op; check(16'h7C00, "Inf*1+0");

        // Test 10: -Inf * 1 + 0 = -Inf
        a = 16'hFC00; b = 16'h3C00; c = 16'h0000;
        run_op; check(16'hFC00, "-Inf*1+0");

        // Test 11: Inf * 0 = NaN
        a = 16'h7C00; b = 16'h0000; c = 16'h0000;
        run_op; check(16'h7E00, "Inf*0+0");

        // Test 12: Inf + Inf = Inf
        a = 16'h7C00; b = 16'h3C00; c = 16'h7C00;
        run_op; check(16'h7C00, "Inf*1+Inf");

        // Test 13: Inf + (-Inf) = NaN
        a = 16'h7C00; b = 16'h3C00; c = 16'hFC00;
        run_op; check(16'h7E00, "Inf*1+(-Inf)");

        // --- Underflow test ---

        // Test 14: smallest denormal * 1 + 0 = denormal (may underflow to zero)
        a = 16'h0001; b = 16'h3C00; c = 16'h0000;
        run_op;
        // Result should be 0x0001 (denormal) or 0x0000 (flush to zero)
        if (result !== 16'h0000 && result !== 16'h0001) begin
            $display("[TB] MISMATCH (underflow): a=%h b=%h c=%h -> got %h, expected 0x0000 or 0x0001", a, b, c, result);
            errors = errors + 1;
        end

        // --- Rounding edge case ---

        // Test 15: 1.0 + 2^(-11) should round to nearest
        // 1.0 = 0x3C00, 2^(-11) = 0x0400
        // 1.0 + 2^(-11) = 1.000488... rounds to 1.0 in FP16 (guard=0)
        a = 16'h3C00; b = 16'h3C00; c = 16'h0400;
        run_op; check(16'h3C00, "1+eps");

        if (errors == 0)
            $display("*** FP16 FMA TEST PASSED ***");
        else
            $display("*** FP16 FMA TEST FAILED (%0d errors) ***", errors);

        $finish;
    end

    initial begin #10000; $display("TIMEOUT"); $finish(1); end

endmodule

HDL/tb_fp16_fma.vcd
$date
	Thu Aug 20 09:14:00 2026
$end
$version
	Icarus Verilog
$end
$timescale
	1ps
$end
$scope module tb_fp16_fma $end
$var wire 1 ! valid_out $end
$var wire 16 " result [15:0] $end
$var reg 16 # a [15:0] $end
$var reg 16 $ b [15:0] $end
$var reg 16 % c [15:0] $end
$var reg 1 & clk $end
$var reg 1 ' rst_n $end
$var reg 1 ( valid_in $end
$var integer 32 ) errors [31:0] $end
$scope module dut $end
$var wire 16 * a [15:0] $end
$var wire 1 + a_den_w $end
$var wire 1 , any_nan $end
$var wire 16 - b [15:0] $end
$var wire 1 . b_den_w $end
$var wire 16 / c [15:0] $end
$var wire 1 0 c_den $end
$var wire 1 & clk $end
$var wire 1 1 inf_add_nan $end
$var wire 1 2 is_special $end
$var wire 1 3 mul_inf $end
$var wire 1 4 mul_inf_zero $end
$var wire 1 5 mul_sign_w $end
$var wire 1 6 result_underflow $end
$var wire 1 7 round_up $end
$var wire 1 8 rounded_carry $end
$var wire 1 ' rst_n $end
$var wire 1 ( valid_in $end
$var wire 1 9 sticky $end
$var wire 16 : special_result [15:0] $end
$var wire 22 ; rounded_man [21:0] $end
$var wire 1 < round $end
$var wire 1 = result_overflow $end
$var wire 16 > packed_result [15:0] $end
$var wire 1 ? mul_ovf_w $end
$var wire 22 @ mul_man_w [21:0] $end
$var wire 22 A mul_man_norm [21:0] $end
$var wire 22 B mul_man_aligned [21:0] $end
$var wire 1 C mul_ge_c $end
$var wire 8 D mul_exp_w [7:0] $end
$var wire 8 E mul_exp_eff [7:0] $end
$var wire 1 F guard $end
$var wire 22 G final_man [21:0] $end
$var wire 8 H final_exp [7:0] $end
$var wire 8 I exp_diff [7:0] $end
$var wire 1 J c_sign $end
$var wire 11 K c_mantissa [10:0] $end
$var wire 22 L c_man_aligned [21:0] $end
$var wire 10 M c_man [9:0] $end
$var wire 6 N c_exponent [5:0] $end
$var wire 5 O c_exp [4:0] $end
$var wire 1 P b_zero_w $end
$var wire 1 Q b_sign_w $end
$var wire 11 R b_mantissa_w [10:0] $end
$var wire 10 S b_man_w [9:0] $end
$var wire 6 T b_exponent_w [5:0] $end
$var wire 5 U b_exp_w [4:0] $end
$var wire 1 V add_sign $end
$var wire 23 W add_result [22:0] $end
$var wire 1 X add_inf $end
$var wire 8 Y add_exp [7:0] $end
$var wire 23 Z abs_diff [22:0] $end
$var wire 1 [ a_zero_w $end
$var wire 1 \ a_sign_w $end
$var wire 11 ] a_mantissa_w [10:0] $end
$var wire 10 ^ a_man_w [9:0] $end
$var wire 6 _ a_exponent_w [5:0] $end
$var wire 5 ` a_exp_w [4:0] $end
$var parameter 32 a FP16_BIAS $end
$var parameter 16 b FP16_INF $end
$var parameter 16 c FP16_NAN $end
$var parameter 16 d FP16_ZERO $end
$var reg 5 e lead_pos [4:0] $end
$var reg 8 f norm_exp [7:0] $end
$var reg 22 g norm_man [21:0] $end
$var reg 1 h norm_sign $end
$var reg 16 i result [15:0] $end
$var reg 16 j s1_a [15:0] $end
$var reg 1 k s1_a_inf $end
$var reg 1 l s1_a_nan $end
$var reg 1 m s1_a_zero $end
$var reg 16 n s1_b [15:0] $end
$var reg 1 o s1_b_inf $end
$var reg 1 p s1_b_nan $end
$var reg 1 q s1_b_zero $end
$var reg 16 r s1_c [15:0] $end
$var reg 1 X s1_c_inf $end
$var reg 1 s s1_c_nan $end
$var reg 1 t s1_c_zero $end
$var reg 8 u s1_mul_exp [7:0] $end
$var reg 22 v s1_mul_man [21:0] $end
$var reg 1 w s1_mul_overflow $end
$var reg 1 x s1_mul_sign $end
$var reg 1 y s1_valid $end
$var reg 16 z s2_result [15:0] $end
$var reg 1 { s2_valid $end
$var reg 1 ! valid_out $end
$var integer 32 | shift [31:0] $end
$upscope $end
$scope task check $end
$var reg 16 } exp [15:0] $end
$var reg 256 ~ name [255:0] $end
$upscope $end
$scope task run_op $end
$upscope $end
$upscope $end
$enddefinitions $end
$comment Show the parameter values. $end
$dumpall
b0 d
b111111000000000 c
b111110000000000 b
b1111 a
$end
#0
$dumpvars
bx ~
bx }
bx |
0{
b0 z
0y
0x
0w
b0 v
b0 u
0t
0s
b0 r
0q
0p
0o
b0 n
0m
0l
0k
b0 j
b0 i
0h
b1000000000000000000000 g
b0 f
bx e
bx `
b0xxxxx _
bx ^
bx ]
x\
x[
b1000000000000000000000 Z
b0 Y
0X
b1000000000000000000000 W
0V
bx U
b0xxxxx T
bx S
bx R
xQ
xP
b0 O
b0 N
b0 M
b1000000000000000000000 L
b10000000000 K
0J
b0 I
b0 H
b1000000000000000000000 G
0F
b0 E
bx D
0C
b0 B
b0 A
bx @
x?
b0 >
0=
0<
b1000000000000000000000 ;
b0 :
09
08
07
16
x5
04
03
02
01
00
bx /
x.
bx -
0,
x+
bx *
b0 )
x(
0'
0&
bx %
bx $
bx #
b0 "
0!
$end
#5000
1&
#10000
0&
#15000
1&
#20000
0&
#25000
x8
x7
xF
x<
x9
bx G
bx ;
bx g
x=
bx >
bx W
b0xxxxx N
bx H
x6
bx Z
bx K
x0
bx f
xh
bx Y
bx B
xC
bx L
x1
x4
bx :
bx A
xV
bx I
bx E
x2
x3
x,
xJ
bx O
bx M
xw
xx
bx u
bx v
xt
xq
xm
xX
xo
xk
xs
xp
xl
xy
bx r
bx n
bx j
1&
1'
#30000
0&
#35000
02
b0 K
00
01
04
b0 N
03
0,
0J
b0 O
b0 M
1t
0q
0m
0X
0o
0k
0s
0p
0l
1y
b0 r
b11110000000000 n
b11110000000000 j
x{
bx z
0?
b100000000000000000000 @
b1111 D
b10000000000 R
b10000000000 ]
b1111 T
b1111 _
0.
0+
05
0Q
b1111 U
b0 S
0P
0\
b1111 `
b0 ^
0[
1&
1(
b0 %
b0 /
b11110000000000 $
b11110000000000 -
b11110000000000 #
b11110000000000 *
#40000
0&
#45000
0=
08
b1000000000000000000000 G
b1000000000000000000000 ;
b11110000000000 :
07
0F
0<
09
b1000000000000000000000 g
b1000000000000000000000 W
b1000000000000000000000 Z
b11110000000000 >
1C
b1111 H
06
b1111 f
0h
b1111 Y
b0 L
b1000000000000000000000 B
0V
b1111 I
b1111 E
b1000000000000000000000 A
x!
bx "
bx i
1{
0w
0x
b1111 u
b100000000000000000000 v
0y
1&
0(
#50000
0&
#55000
0{
b11110000000000 z
1!
1&
#60000
0&
#65000
0!
b11110000000000 "
b11110000000000 i
1&
#70000
0&
#75000
b100000000000000 :
b100000000000000 >
b10000 H
b10000 f
b0 Z
b10000000000000000000000 W
b1000000000000000000000 L
b0 I
b1111 N
b10000000000 K
b1111 O
0t
1y
b11110000000000 r
b100001000000000 n
b100000000000000 j
b110000000000000000000 @
b11000000000 R
b10001 D
b10000 T
b10000 _
b10000 U
b1000000000 S
b10000 `
1(
b11110000000000 %
b11110000000000 /
b100001000000000 $
b100001000000000 -
b100000000000000 #
b100000000000000 *
b11000100101010001100010010101100110000 ~
b11110000000000 }
1&
#80000
0&
#85000
b100011100000000 :
b100011100000000 >
b1110000000000000000000 G
b1110000000000000000000 ;
b1110000000000000000000 g
b10001 H
b1010000000000000000000 Z
b1110000000000000000000 W
b1100000000000000000000 B
b10001 f
b1100000000000000000000 A
b10001 Y
b10000000000000000000 L
b10 I
b10001 E
1{
b100000000000000 z
b10001 u
b110000000000000000000 v
0y
1&
0(
#90000
0&
#95000
0{
b100011100000000 z
1!
b100000000000000 "
b100000000000000 i
1&
#100000
0&
#105000
0!
b100011100000000 "
b100011100000000 i
1&
#110000
0&
#115000
b100011000000000 :
b100011000000000 >
09
b1100000000000000000000 G
b1100000000000000000000 ;
b1100000000000000000000 g
b1100000000000000000000 Z
b1100000000000000000000 W
b0 L
b0 K
b10001 I
b0 N
b0 O
1t
1y
b0 r
b11100000000000 n
b11100000000000 j
b100000000000000000000 @
b10000000000 R
b1101 D
b1110 T
b1110 _
b1110 U
b0 S
b1110 `
1(
b0 %
b0 /
b11100000000000 $
b11100000000000 -
b11100000000000 #
b11100000000000 *
b11001000101010001100110010101100110001 ~
b100011100000000 }
1&
#120000
0&
#125000
b11010000000000 :
b11010000000000 >
b1000000000000000000000 G
b1000000000000000000000 ;
b1000000000000000000000 g
b1000000000000000000000 Z
b1000000000000000000000 W
b1101 H
b1000000000000000000000 B
b1101 f
b1000000000000000000000 A
b1101 Y
b1101 I
b1101 E
1{
b100011000000000 z
b1101 u
b100000000000000000000 v
0y
1&
0(
#130000
0&
#135000
0{
b11010000000000 z
1!
b100011000000000 "
b100011000000000 i
1&
#140000
0&
#145000
0!
b11010000000000 "
b11010000000000 i
1&
#150000
0&
#155000
1q
1y
b0 n
b11110000000000 j
b0 R
b1111 _
b0 @
b0 D
b0 T
b0 U
1P
b1111 `
1(
b0 $
b0 -
b11110000000000 #
b11110000000000 *
b1100000010111000110101001010100011000000101110001101010010101100110000 ~
b11010000000000 }
1&
#160000
0&
#165000
b0 :
b0 G
b0 ;
b0 g
b0 >
b0 Z
b0 W
16
b0 H
b0 B
b0 f
b0 A
b0 Y
b0 I
b0 E
1{
b0 u
b0 v
0y
1&
0(
#170000
0&
#175000
0{
b0 z
1!
1&
#180000
0&
#185000
0!
b0 "
b0 i
1&
#190000
0&
#195000
b100001000000000 :
b100001000000000 >
06
08
b10000 H
b1100000000000000000000 G
b10000 f
b1100000000000000000000 ;
b1100000000000000000000 g
b1100000000000000000000 W
b1100000000000000000000 Z
b10000 Y
0C
b1100000000000000000000 L
b11110000 I
b10000 N
b11000000000 K
b10000 O
b1000000000 M
0t
0q
1y
b100001000000000 r
b100000000000000 n
b1011110000000000 j
b10000 D
b100000000000000000000 @
b10000 T
b10000000000 R
15
b10000 U
0P
1\
1(
b100001000000000 %
b100001000000000 /
b100000000000000 $
b100000000000000 -
b1011110000000000 #
b1011110000000000 *
b11000100101010001100000010101100110000 ~
b0 }
1&
#200000
0&
#205000
b11110000000000 :
b11110000000000 >
b1111 H
b1000000000000000000000 G
b1111 f
b1 |
b1 e
b1000000000000000000000 ;
b1000000000000000000000 g
b100000000000000000000 W
b100000000000000000000 Z
b1000000000000000000000 B
b1000000000000000000000 A
b0 I
b10000 E
1{
b100001000000000 z
1x
b10000 u
b100000000000000000000 v
0y
1&
0(
#210000
0&
#215000
0{
b11110000000000 z
1!
b100001000000000 "
b100001000000000 i
1&
#220000
0&
#225000
0!
b11110000000000 "
b11110000000000 i
1&
#230000
0&
#235000
b10000 H
b1100000000000000 >
07
0F
0<
09
b1000000000000000000000 G
b1 e
b10000 f
b1000000000000000000000 ;
b1000000000000000000000 g
1h
b1000000000000000000000 W
1V
12
b1000000000000000000000 Z
1C
b0 L
b0 K
b111111000000000 :
b10000 I
1,
b0 N
b0 O
b0 M
1t
1l
1y
b0 r
b11110000000000 n
b111111000000000 j
b110000000000000000000 @
b11111 D
b11000000000 ]
b1111 T
b11111 _
05
b1111 U
0\
b11111 `
b1000000000 ^
1(
b0 %
b0 /
b11110000000000 $
b11110000000000 -
b111111000000000 #
b111111000000000 *
b1011010011000100101010001100100010101100110011 ~
b11110000000000 }
1&
#240000
0&
#245000
b1100000000000000000000 G
b1100000000000000000000 ;
b1100000000000000000000 g
b111110000000000 >
b1100000000000000000000 Z
b1100000000000000000000 W
1=
b11111 H
b1100000000000000000000 B
b11111 f
0h
b1100000000000000000000 A
0V
b11111 Y
b11111 I
b11111 E
1{
b111111000000000 z
0x
b11111 u
b110000000000000000000 v
0y
1&
0(
#250000
0&
#255000
0{
1!
b111111000000000 "
b111111000000000 i
1&
#260000
0&
#265000
0!
1&
#270000
0&
#275000
1p
0l
1y
b111111000000000 n
b11110000000000 j
b11000000000 R
b10000000000 ]
b11111 T
b1111 _
b11111 U
b1000000000 S
b1111 `
b0 ^
1(
b111111000000000 $
b111111000000000 -
b11110000000000 #
b11110000000000 *
b1001110011000010100111000101010001100010010101100110000 ~
b111111000000000 }
1&
#280000
0&
#285000
1{
0y
1&
0(
#290000
0&
#295000
0{
1!
1&
#300000
0&
#305000
0!
1&
#310000
0&
#315000
b100000 H
b1100000000000000000000 G
b100000 f
b1100000000000000000000 ;
b1100000000000000000000 g
b0 Z
b11000000000000000000000 W
b1100000000000000000000 L
b0 I
b11111 N
b11000000000 K
b11111 O
b1000000000 M
0t
1s
0p
1l
1y
b111111000000000 r
b11110000000000 n
b111111000000000 j
b10000000000 R
b11000000000 ]
b1111 T
b11111 _
b1111 U
b0 S
b11111 `
b1000000000 ^
1(
b111111000000000 %
b111111000000000 /
b11110000000000 $
b11110000000000 -
b111111000000000 #
b111111000000000 *
b110001001010100100111001100001010011100010101100110000 ~
1&
#320000
0&
#325000
1{
0y
1&
0(
#330000
0&
#335000
0{
1!
1&
#340000
0&
#345000
0!
1&
#350000
0&
#355000
b11111 H
b11111 f
b1100000000000000000000 Z
b1100000000000000000000 W
b0 L
b0 K
b11111 I
b111110000000000 :
b0 N
13
0,
b0 O
b0 M
1t
1k
0s
0l
1y
b0 r
b111110000000000 j
b100000000000000000000 @
b10000000000 ]
b0 ^
1(
b0 %
b0 /
b111110000000000 #
b111110000000000 *
b10011100110000101001110001010100011000100101011010011100110000101001110 ~
1&
#360000
0&
#365000
b1000000000000000000000 G
b1000000000000000000000 ;
b1000000000000000000000 g
b1000000000000000000000 Z
b1000000000000000000000 W
b1000000000000000000000 B
b1000000000000000000000 A
1{
b111110000000000 z
b100000000000000000000 v
0y
1&
0(
#370000
0&
#375000
0{
1!
b111110000000000 "
b111110000000000 i
1&
#380000
0&
#385000
0!
1&
#390000
0&
#395000
1y
b1111110000000000 j
15
1\
1(
b1111110000000000 #
b1111110000000000 *
b1001001011011100110011000101010001100010010101100110000 ~
b111110000000000 }
1&
#400000
0&
#405000
b1111110000000000 >
b1111110000000000 :
1h
1V
1{
1x
0y
1&
0(
#410000
0&
#415000
0{
b1111110000000000 z
1!
1&
#420000
0&
#425000
0!
b1111110000000000 "
b1111110000000000 i
1&
#430000
0&
