HDL/fp16_fma.v
`timescale 1ns/1ps

// =============================================================================
// fp16_fma — IEEE 754 half-precision Fused Multiply-Add unit
//
// Computes: result = (a * b) + c  in FP16 (binary16) format.
// Pipeline latency: 3 cycles (matching MULT_LATENCY in pe_tile_stub.v).
//
// IEEE 754 half-precision format:
//   [15]    sign
//   [14:10] exponent (5 bits, bias = 15)
//   [9:0]   mantissa (10 bits, implicit leading 1)
//
// Fixes applied:
//   1. Pipeline: multiply results registered into stage 1 (s1_mul_*)
//   2. Underflow: signed norm_exp prevents unsigned wrap to infinity
//   3. Rounding: round-to-nearest-even with guard/round/sticky bits
//   4. Special cases: NaN, Inf, zero*Inf properly handled
// =============================================================================

module fp16_fma (
    input  wire        clk,
    input  wire        rst_n,
    input  wire [15:0] a,
    input  wire [15:0] b,
    input  wire [15:0] c,
    input  wire        valid_in,
    output reg  [15:0] result,
    output reg         valid_out
);

    localparam FP16_BIAS = 15;
    localparam FP16_ZERO = 16'h0000;
    localparam FP16_INF  = 16'h7C00;
    localparam FP16_NAN  = 16'h7E00;

    // =========================================================================
    // Pipeline stage 1: register inputs + detect special cases + multiply
    // =========================================================================
    reg [15:0] s1_a, s1_b, s1_c;
    reg        s1_valid;

    // Special case flags (registered with inputs)
    reg s1_a_nan, s1_b_nan, s1_c_nan;
    reg s1_a_inf, s1_b_inf, s1_c_inf;
    reg s1_a_zero, s1_b_zero, s1_c_zero;

    // Registered multiply results (fix #1: must travel with s1_c)
    reg [21:0] s1_mul_man;
    reg [6:0]  s1_mul_exp;
    reg        s1_mul_sign;
    reg        s1_mul_overflow;

    // Unpack a (combinational from current inputs)
    wire        a_sign_w = a[15];
    wire [4:0]  a_exp_w  = a[14:10];
    wire [9:0]  a_man_w  = a[9:0];
    wire        a_zero_w = (a == 16'h0000);
    wire        a_den_w  = (a_exp_w == 0) && (a_man_w != 0);

    wire [10:0] a_mantissa_w;
    assign a_mantissa_w[10]   = (a_zero_w || a_den_w) ? 1'b0 : 1'b1;
    assign a_mantissa_w[9:0]  = a_zero_w ? 10'd0 : (a_den_w ? {1'b0, a_man_w} : a_man_w);
    wire [5:0]  a_exponent_w = a_zero_w ? 6'd0 : (a_den_w ? 6'd1 : {1'b0, a_exp_w});

    // Unpack b (combinational from current inputs)
    wire        b_sign_w = b[15];
    wire [4:0]  b_exp_w  = b[14:10];
    wire [9:0]  b_man_w  = b[9:0];
    wire        b_zero_w = (b == 16'h0000);
    wire        b_den_w  = (b_exp_w == 0) && (b_man_w != 0);

    wire [10:0] b_mantissa_w;
    assign b_mantissa_w[10]   = (b_zero_w || b_den_w) ? 1'b0 : 1'b1;
    assign b_mantissa_w[9:0]  = b_zero_w ? 10'd0 : (b_den_w ? {1'b0, b_man_w} : b_man_w);
    wire [5:0]  b_exponent_w = b_zero_w ? 6'd0 : (b_den_w ? 6'd1 : {1'b0, b_exp_w});

    // Multiply (combinational, registered next cycle)
    wire        mul_sign_w = a_sign_w ^ b_sign_w;
    wire [6:0]  mul_exp_w  = a_exponent_w + b_exponent_w - FP16_BIAS;
    wire [21:0] mul_man_w  = a_mantissa_w * b_mantissa_w;
    wire        mul_ovf_w  = mul_man_w[21];

    always @(posedge clk or negedge rst_n) begin
        if (!rst_n) begin
            s1_a <= 0; s1_b <= 0; s1_c <= 0;
            s1_valid <= 0;
            s1_a_nan <= 0; s1_b_nan <= 0; s1_c_nan <= 0;
            s1_a_inf <= 0; s1_b_inf <= 0; s1_c_inf <= 0;
            s1_a_zero <= 0; s1_b_zero <= 0; s1_c_zero <= 0;
            s1_mul_man <= 0; s1_mul_exp <= 0;
            s1_mul_sign <= 0; s1_mul_overflow <= 0;
        end else begin
            s1_a <= a; s1_b <= b; s1_c <= c;
            s1_valid <= valid_in;
            s1_a_nan   <= (a[14:10] == 5'd31) && (a[9:0] != 10'd0);
            s1_b_nan   <= (b[14:10] == 5'd31) && (b[9:0] != 10'd0);
            s1_c_nan   <= (c[14:10] == 5'd31) && (c[9:0] != 10'd0);
            s1_a_inf   <= (a[14:10] == 5'd31) && (a[9:0] == 10'd0);
            s1_b_inf   <= (b[14:10] == 5'd31) && (b[9:0] == 10'd0);
            s1_c_inf   <= (c[14:10] == 5'd31) && (c[9:0] == 10'd0);
            s1_a_zero  <= (a == 16'h0000);
            s1_b_zero  <= (b == 16'h0000);
            s1_c_zero  <= (c == 16'h0000);
            s1_mul_man      <= mul_man_w;
            s1_mul_exp      <= mul_exp_w;
            s1_mul_sign     <= mul_sign_w;
            s1_mul_overflow <= mul_ovf_w;
        end
    end

    // =========================================================================
    // Pipeline stage 2: align, add, normalize, round, pack
    // =========================================================================

    // Unpack s1_c (the addend, from registered s1_c)
    wire        c_sign = s1_c[15];
    wire [4:0]  c_exp  = s1_c[14:10];
    wire [9:0]  c_man  = s1_c[9:0];
    wire        c_den  = (c_exp == 0) && (c_man != 0);

    wire [10:0] c_mantissa;
    assign c_mantissa[10]   = (s1_c_zero || c_den) ? 1'b0 : 1'b1;
    assign c_mantissa[9:0]  = s1_c_zero ? 10'd0 : (c_den ? {1'b0, c_man} : c_man);
    wire [5:0]  c_exponent = s1_c_zero ? 6'd0 : (c_den ? 6'd1 : {1'b0, c_exp});

    // Effective multiply exponent (from registered multiply results)
    wire [6:0]  mul_exp_eff = s1_mul_overflow ? (s1_mul_exp + 7'd1) : s1_mul_exp;

    // Result exponent: max(mul_exp_eff, c_exponent)
    wire [6:0]  add_exp = (mul_exp_eff > {1'b0, c_exponent}) ? mul_exp_eff : {1'b0, c_exponent};

    // Align mantissas: both have implicit 1 at bit 21
    wire [21:0] mul_man_aligned = (mul_exp_eff >= {1'b0, c_exponent}) ?
        (s1_mul_man << 1) :
        (s1_mul_man << 1) >> ({1'b0, c_exponent} - mul_exp_eff);
    wire [21:0] c_man_aligned = ({1'b0, c_exponent} > mul_exp_eff) ?
        ({c_mantissa, 11'd0}) :
        ({c_mantissa, 11'd0} >> (mul_exp_eff - {1'b0, c_exponent}));

    // Add with sign/magnitude
    wire        mul_ge_c = (mul_man_aligned >= c_man_aligned);
    wire [22:0] abs_diff = mul_ge_c ?
        ({1'b0, mul_man_aligned} - {1'b0, c_man_aligned}) :
        ({1'b0, c_man_aligned} - {1'b0, mul_man_aligned});

    wire        add_sign = (s1_mul_sign == c_sign) ? s1_mul_sign :
                           mul_ge_c ? s1_mul_sign : c_sign;
    wire [22:0] add_result = (s1_mul_sign == c_sign) ?
        ({1'b0, mul_man_aligned} + {1'b0, c_man_aligned}) :
        abs_diff;

    // Normalize (fix #2: signed exponent prevents underflow wrap)
    reg [21:0] norm_man;
    reg signed [7:0] norm_exp;
    reg        norm_sign;
    reg [4:0]  lead_pos;
    integer shift;

    always @(*) begin
        norm_sign = add_sign;
        if (add_result == 0) begin
            norm_man = 0;
            norm_exp = 0;
        end else if (add_result[22]) begin
            norm_man = add_result[22:1];
            norm_exp = add_exp + 1;
        end else begin
            norm_man = add_result[21:0];
            norm_exp = {1'b0, add_exp};
            if (!norm_man[21]) begin
                lead_pos = 0;
                if      (norm_man[20]) lead_pos = 1;
                else if (norm_man[19]) lead_pos = 2;
                else if (norm_man[18]) lead_pos = 3;
                else if (norm_man[17]) lead_pos = 4;
                else if (norm_man[16]) lead_pos = 5;
                else if (norm_man[15]) lead_pos = 6;
                else if (norm_man[14]) lead_pos = 7;
                else if (norm_man[13]) lead_pos = 8;
                else if (norm_man[12]) lead_pos = 9;
                else if (norm_man[11]) lead_pos = 10;
                else if (norm_man[10]) lead_pos = 11;
                else if (norm_man[9])  lead_pos = 12;
                else if (norm_man[8])  lead_pos = 13;
                else if (norm_man[7])  lead_pos = 14;
                else if (norm_man[6])  lead_pos = 15;
                else if (norm_man[5])  lead_pos = 16;
                else if (norm_man[4])  lead_pos = 17;
                else if (norm_man[3])  lead_pos = 18;
                else if (norm_man[2])  lead_pos = 19;
                else if (norm_man[1])  lead_pos = 20;
                else                   lead_pos = 21;
                shift = lead_pos;
                norm_man = norm_man << shift;
                norm_exp = norm_exp - shift;
            end
        end
    end

    // Round-to-nearest-even (fix #3)
    // After normalization, implicit 1 at bit 21.
    // Mantissa field: norm_man[20:11] (10 bits)
    // Guard bit: norm_man[10], Round: norm_man[9], Sticky: |norm_man[8:0]
    wire guard  = norm_man[10];
    wire round  = norm_man[9];
    wire sticky = |norm_man[8:0];

    // Round up if: guard=1 AND (round=1 OR sticky=1 OR LSB of mantissa=1)
    wire round_up = guard & (round | sticky | norm_man[11]);

    // Apply rounding: add 1 at bit position 10 (LSB of mantissa field in norm_man)
    wire [21:0] rounded_man = norm_man + (round_up ? 22'd1024 : 22'd0);

    // Detect carry from rounding (bit 21 went from 1 to 0 = overflow)
    wire rounded_carry = ~rounded_man[21] & norm_man[21];

    wire [21:0] final_man = rounded_carry ? 22'h002000 : rounded_man;  // 1<<21
    wire [7:0]  final_exp = rounded_carry ? (norm_exp + 8'd1) : norm_exp;

    // Pack result
    // Underflow: norm_exp < 0 (signed), or norm_exp == 0 with no rounding carry
    wire result_underflow = (norm_exp < 0) || (norm_exp == 0 && !rounded_carry);
    wire result_overflow  = (final_exp >= 31);
    wire [15:0] packed_result;
    assign packed_result = result_underflow ? FP16_ZERO :
                           result_overflow  ? FP16_INF  :
                           {norm_sign, final_exp[4:0], final_man[20:11]};

    // =========================================================================
    // Special case handling (fix #4)
    // =========================================================================
    // NaN * anything = NaN
    // Inf * 0 = NaN
    // Inf * finite = Inf (with sign)
    // finite * Inf = Inf (with sign)
    // NaN + anything = NaN
    // Inf + anything = Inf (unless Inf + (-Inf) = NaN)
    wire any_nan = s1_a_nan | s1_b_nan | s1_c_nan;
    wire mul_inf_zero = (s1_a_inf & s1_b_zero) | (s1_b_inf & s1_a_zero);
    wire mul_inf = s1_a_inf | s1_b_inf;
    wire add_inf = s1_c_inf;

    // Check if we are doing Inf + (-Inf) for the addend (which = NaN)
    // This happens when: (a*b) produced Inf with some sign, and c is Inf with opposite sign
    wire inf_add_nan = mul_inf & add_inf & (s1_mul_sign != c_sign);

    wire is_special = any_nan | mul_inf_zero | mul_inf | add_inf;

    wire [15:0] special_result =
        any_nan      ? FP16_NAN :
        mul_inf_zero ? FP16_NAN :
        inf_add_nan  ? FP16_NAN :
        mul_inf      ? {s1_mul_sign, 5'd31, 10'd0} :
        add_inf      ? s1_c :
                       packed_result;

    reg [15:0] s2_result;
    reg        s2_valid;
    reg        s2_sign;

    always @(posedge clk or negedge rst_n) begin
        if (!rst_n) begin
            s2_result <= 0;
            s2_valid  <= 0;
            s2_sign   <= 0;
        end else begin
            s2_result <= is_special ? special_result : packed_result;
            s2_valid  <= s1_valid;
            s2_sign   <= norm_sign;
        end
    end

    // =========================================================================
    // Pipeline stage 3: output register
    // =========================================================================
    always @(posedge clk or negedge rst_n) begin
        if (!rst_n) begin
            result    <= 0;
            valid_out <= 0;
        end else begin
            result    <= s2_result;
            valid_out <= s2_valid;
        end
    end

endmodule

HDL/tb_fp16_fma.v
`timescale 1ns/1ps

// =============================================================================
// tb_fp16_fma — self-checking testbench for FP16 FMA unit
// Tests: basic ops, NaN propagation, Inf arithmetic, underflow, rounding
// =============================================================================
module tb_fp16_fma;

    reg         clk = 0;
    reg         rst_n = 0;
    reg  [15:0] a, b, c;
    reg         valid_in;
    wire [15:0] result;
    wire        valid_out;

    always #5 clk = ~clk;

    fp16_fma dut (
        .clk(clk), .rst_n(rst_n),
        .a(a), .b(b), .c(c), .valid_in(valid_in),
        .result(result), .valid_out(valid_out)
    );

    integer errors;

    task check;
        input [15:0] exp;
        input [8*32-1:0] name;
        begin
            if (result !== exp) begin
                $display("[TB] MISMATCH (%0s): a=%h b=%h c=%h -> got %h, expected %h", name, a, b, c, result, exp);
                errors = errors + 1;
            end
        end
    endtask

    task run_op;
        begin
            valid_in = 1; #10; valid_in = 0;
            repeat (4) @(posedge clk);
        end
    endtask

    initial begin
        $dumpfile("tb_fp16_fma.vcd");
        $dumpvars(0, tb_fp16_fma);
        errors = 0;

        // Reset
        #25; rst_n = 1; #10;

        // --- Basic operations ---

        // Test 1: 1.0 * 1.0 + 0.0 = 1.0
        a = 16'h3C00; b = 16'h3C00; c = 16'h0000;
        run_op; check(16'h3C00, "1*1+0");

        // Test 2: 2.0 * 3.0 + 1.0 = 7.0
        a = 16'h4000; b = 16'h4200; c = 16'h3C00;
        run_op; check(16'h4700, "2*3+1");

        // Test 3: 0.5 * 0.5 + 0.0 = 0.25
        a = 16'h3800; b = 16'h3800; c = 16'h0000;
        run_op; check(16'h3400, "0.5*0.5+0");

        // Test 4: 1.0 * 0.0 + 0.0 = 0.0
        a = 16'h3C00; b = 16'h0000; c = 16'h0000;
        run_op; check(16'h0000, "1*0+0");

        // Test 5: -1.0 * 2.0 + 3.0 = 1.0
        a = 16'hBC00; b = 16'h4000; c = 16'h4200;
        run_op; check(16'h3C00, "-1*2+3");

        // --- NaN tests ---

        // Test 6: NaN * anything = NaN
        a = 16'h7E00; b = 16'h3C00; c = 16'h0000;
        run_op; check(16'h7E00, "NaN*1+0");

        // Test 7: anything * NaN = NaN
        a = 16'h3C00; b = 16'h7E00; c = 16'h0000;
        run_op; check(16'h7E00, "1*NaN+0");

        // Test 8: NaN + NaN = NaN
        a = 16'h7E00; b = 16'h3C00; c = 16'h7E00;
        run_op; check(16'h7E00, "NaN*1+NaN");

        // --- Infinity tests ---

        // Test 9: Inf * 1 + 0 = Inf
        a = 16'h7C00; b = 16'h3C00; c = 16'h0000;
        run_op; check(16'h7C00, "Inf*1+0");

        // Test 10: -Inf * 1 + 0 = -Inf
        a = 16'hFC00; b = 16'h3C00; c = 16'h0000;
        run_op; check(16'hFC00, "-Inf*1+0");

        // Test 11: Inf * 0 = NaN
        a = 16'h7C00; b = 16'h0000; c = 16'h0000;
        run_op; check(16'h7E00, "Inf*0+0");

        // Test 12: Inf + Inf = Inf
        a = 16'h7C00; b = 16'h3C00; c = 16'h7C00;
        run_op; check(16'h7C00, "Inf*1+Inf");

        // Test 13: Inf + (-Inf) = NaN
        a = 16'h7C00; b = 16'h3C00; c = 16'hFC00;
        run_op; check(16'h7E00, "Inf*1+(-Inf)");

        // --- Underflow test ---

        // Test 14: smallest denormal * 1 + 0 = denormal (may underflow to zero)
        a = 16'h0001; b = 16'h3C00; c = 16'h0000;
        run_op;
        // Result should be 0x0001 (denormal) or 0x0000 (flush to zero)
        if (result !== 16'h0000 && result !== 16'h0001) begin
            $display("[TB] MISMATCH (underflow): a=%h b=%h c=%h -> got %h, expected 0x0000 or 0x0001", a, b, c, result);
            errors = errors + 1;
        end

        // --- Rounding edge case ---

        // Test 15: 1.0 + 2^(-11) should round to nearest
        // 1.0 = 0x3C00, 2^(-11) = 0x0400
        // 1.0 + 2^(-11) = 1.000488... rounds to 1.0 in FP16 (guard=0)
        a = 16'h3C00; b = 16'h3C00; c = 16'h0400;
        run_op; check(16'h3C00, "1+eps");

        if (errors == 0)
            $display("*** FP16 FMA TEST PASSED ***");
        else
            $display("*** FP16 FMA TEST FAILED (%0d errors) ***", errors);

        $finish;
    end

    initial begin #10000; $display("TIMEOUT"); $finish(1); end

endmodule

HDL/tb_fp16_fma.vcd
$date
	Tue Aug 18 01:44:24 2026
$end
$version
	Icarus Verilog
$end
$timescale
	1ps
$end
$scope module tb_fp16_fma $end
$var wire 1 ! valid_out $end
$var wire 16 " result [15:0] $end
$var reg 16 # a [15:0] $end
$var reg 16 $ b [15:0] $end
$var reg 16 % c [15:0] $end
$var reg 1 & clk $end
$var reg 1 ' rst_n $end
$var reg 1 ( valid_in $end
$var integer 32 ) errors [31:0] $end
$scope module dut $end
$var wire 16 * a [15:0] $end
$var wire 1 + a_den_w $end
$var wire 1 , any_nan $end
$var wire 16 - b [15:0] $end
$var wire 1 . b_den_w $end
$var wire 16 / c [15:0] $end
$var wire 1 0 c_den $end
$var wire 1 & clk $end
$var wire 1 1 inf_add_nan $end
$var wire 1 2 is_special $end
$var wire 1 3 mul_inf $end
$var wire 1 4 mul_inf_zero $end
$var wire 1 5 mul_sign_w $end
$var wire 1 6 result_underflow $end
$var wire 1 7 round_up $end
$var wire 1 8 rounded_carry $end
$var wire 1 ' rst_n $end
$var wire 1 ( valid_in $end
$var wire 1 9 sticky $end
$var wire 16 : special_result [15:0] $end
$var wire 22 ; rounded_man [21:0] $end
$var wire 1 < round $end
$var wire 1 = result_overflow $end
$var wire 16 > packed_result [15:0] $end
$var wire 1 ? mul_ovf_w $end
$var wire 22 @ mul_man_w [21:0] $end
$var wire 22 A mul_man_aligned [21:0] $end
$var wire 1 B mul_ge_c $end
$var wire 7 C mul_exp_w [6:0] $end
$var wire 7 D mul_exp_eff [6:0] $end
$var wire 1 E guard $end
$var wire 22 F final_man [21:0] $end
$var wire 8 G final_exp [7:0] $end
$var wire 1 H c_sign $end
$var wire 11 I c_mantissa [10:0] $end
$var wire 22 J c_man_aligned [21:0] $end
$var wire 10 K c_man [9:0] $end
$var wire 6 L c_exponent [5:0] $end
$var wire 5 M c_exp [4:0] $end
$var wire 1 N b_zero_w $end
$var wire 1 O b_sign_w $end
$var wire 11 P b_mantissa_w [10:0] $end
$var wire 10 Q b_man_w [9:0] $end
$var wire 6 R b_exponent_w [5:0] $end
$var wire 5 S b_exp_w [4:0] $end
$var wire 1 T add_sign $end
$var wire 23 U add_result [22:0] $end
$var wire 1 V add_inf $end
$var wire 7 W add_exp [6:0] $end
$var wire 23 X abs_diff [22:0] $end
$var wire 1 Y a_zero_w $end
$var wire 1 Z a_sign_w $end
$var wire 11 [ a_mantissa_w [10:0] $end
$var wire 10 \ a_man_w [9:0] $end
$var wire 6 ] a_exponent_w [5:0] $end
$var wire 5 ^ a_exp_w [4:0] $end
$var parameter 32 _ FP16_BIAS $end
$var parameter 16 ` FP16_INF $end
$var parameter 16 a FP16_NAN $end
$var parameter 16 b FP16_ZERO $end
$var reg 5 c lead_pos [4:0] $end
$var reg 8 d norm_exp [7:0] $end
$var reg 22 e norm_man [21:0] $end
$var reg 1 f norm_sign $end
$var reg 16 g result [15:0] $end
$var reg 16 h s1_a [15:0] $end
$var reg 1 i s1_a_inf $end
$var reg 1 j s1_a_nan $end
$var reg 1 k s1_a_zero $end
$var reg 16 l s1_b [15:0] $end
$var reg 1 m s1_b_inf $end
$var reg 1 n s1_b_nan $end
$var reg 1 o s1_b_zero $end
$var reg 16 p s1_c [15:0] $end
$var reg 1 V s1_c_inf $end
$var reg 1 q s1_c_nan $end
$var reg 1 r s1_c_zero $end
$var reg 7 s s1_mul_exp [6:0] $end
$var reg 22 t s1_mul_man [21:0] $end
$var reg 1 u s1_mul_overflow $end
$var reg 1 v s1_mul_sign $end
$var reg 1 w s1_valid $end
$var reg 16 x s2_result [15:0] $end
$var reg 1 y s2_sign $end
$var reg 1 z s2_valid $end
$var reg 1 ! valid_out $end
$var integer 32 { shift [31:0] $end
$upscope $end
$scope task check $end
$var reg 16 | exp [15:0] $end
$var reg 256 } name [255:0] $end
$upscope $end
$scope task run_op $end
$upscope $end
$upscope $end
$enddefinitions $end
$comment Show the parameter values. $end
$dumpall
b0 b
b111111000000000 a
b111110000000000 `
b1111 _
$end
#0
$dumpvars
bx }
bx |
bx {
0z
0y
b0 x
0w
0v
0u
b0 t
b0 s
0r
0q
b0 p
0o
0n
0m
b0 l
0k
0j
0i
b0 h
b0 g
0f
b1000000000000000000000 e
b0 d
bx c
bx ^
b0xxxxx ]
bx \
bx [
xZ
xY
b1000000000000000000000 X
b0 W
0V
b1000000000000000000000 U
0T
bx S
b0xxxxx R
bx Q
bx P
xO
xN
b0 M
b0 L
b0 K
b1000000000000000000000 J
b10000000000 I
0H
b0 G
b1000000000000000000000 F
0E
b0 D
bx C
0B
b0 A
bx @
x?
b0 >
0=
0<
b1000000000000000000000 ;
b0 :
09
08
07
16
x5
04
03
02
01
00
bx /
x.
bx -
0,
x+
bx *
b0 )
x(
0'
0&
bx %
bx $
bx #
b0 "
0!
$end
#5000
1&
#10000
0&
#15000
1&
#20000
0&
#25000
x8
x7
xE
x<
x9
bx F
bx ;
bx e
x=
bx >
bx U
b0xxxxx L
bx G
x6
bx X
bx I
x0
b0xxxxxxx d
xf
bx W
bx A
xB
bx J
x1
x4
bx :
xT
bx D
x2
x3
x,
xH
bx M
bx K
xu
xv
bx s
bx t
xr
xo
xk
xV
xm
xi
xq
xn
xj
xw
bx p
bx l
bx h
1&
1'
#30000
0&
#35000
02
b0 I
00
01
04
b0 L
03
0,
0H
b0 M
b0 K
1r
0o
0k
0V
0m
0i
0q
0n
0j
1w
b0 p
b11110000000000 l
b11110000000000 h
xy
xz
bx x
0?
b100000000000000000000 @
b1111 C
b10000000000 P
b10000000000 [
b1111 R
b1111 ]
0.
0+
05
0O
b1111 S
b0 Q
0Z
b1111 ^
b0 \
1&
1(
b0 %
b0 /
0N
b11110000000000 $
b11110000000000 -
0Y
b11110000000000 #
b11110000000000 *
#40000
0&
#45000
0=
08
b11110000000000 :
b1000000000000000000000 F
b1000000000000000000000 ;
07
0E
0<
09
b1000000000000000000000 e
b11110000000000 >
b1000000000000000000000 U
b1111 G
06
b1000000000000000000000 X
b1111 d
0f
b1111 W
1B
b1000000000000000000000 A
b0 J
0T
b1111 D
x!
bx "
bx g
1z
0u
0v
b1111 s
b100000000000000000000 t
0w
1&
0(
#50000
0&
#55000
0y
0z
b11110000000000 x
1!
1&
#60000
0&
#65000
0!
b11110000000000 "
b11110000000000 g
1&
#70000
0&
#75000
b100000000000000 :
b100000000000000 >
b10000 G
b10000 d
b0 X
b10000000000000000000000 U
b1000000000000000000000 J
b1111 L
b10000000000 I
b1111 M
0r
1w
b11110000000000 p
b100001000000000 l
b100000000000000 h
b110000000000000000000 @
b11000000000 P
b10001 C
b10000 R
b10000 ]
b10000 S
b1000000000 Q
b10000 ^
1(
b11110000000000 %
b11110000000000 /
b100001000000000 $
b100001000000000 -
b100000000000000 #
b100000000000000 *
b11000100101010001100010010101100110000 }
b11110000000000 |
1&
#80000
0&
#85000
b100011100000000 :
b100011100000000 >
b1110000000000000000000 F
b1110000000000000000000 ;
b1110000000000000000000 e
b10001 G
b1010000000000000000000 X
b1110000000000000000000 U
b10001 d
b1100000000000000000000 A
b10001 W
b10000000000000000000 J
b10001 D
1z
b100000000000000 x
b10001 s
b110000000000000000000 t
0w
1&
0(
#90000
0&
#95000
0z
b100011100000000 x
1!
b100000000000000 "
b100000000000000 g
1&
#100000
0&
#105000
0!
b100011100000000 "
b100011100000000 g
1&
#110000
0&
#115000
b100011000000000 :
b100011000000000 >
09
b1100000000000000000000 F
b1100000000000000000000 ;
b1100000000000000000000 e
b1100000000000000000000 X
b1100000000000000000000 U
b0 J
b0 I
b0 L
b0 M
1r
1w
b0 p
b11100000000000 l
b11100000000000 h
b100000000000000000000 @
b10000000000 P
b1101 C
b1110 R
b1110 ]
b1110 S
b0 Q
b1110 ^
1(
b0 %
b0 /
b11100000000000 $
b11100000000000 -
b11100000000000 #
b11100000000000 *
b11001000101010001100110010101100110001 }
b100011100000000 |
1&
#120000
0&
#125000
b11010000000000 :
b11010000000000 >
b1000000000000000000000 F
b1000000000000000000000 ;
b1000000000000000000000 e
b1000000000000000000000 X
b1000000000000000000000 U
b1101 G
b1101 d
b1000000000000000000000 A
b1101 W
b1101 D
1z
b100011000000000 x
b1101 s
b100000000000000000000 t
0w
1&
0(
#130000
0&
#135000
0z
b11010000000000 x
1!
b100011000000000 "
b100011000000000 g
1&
#140000
0&
#145000
0!
b11010000000000 "
b11010000000000 g
1&
#150000
0&
#155000
1o
1w
b0 l
b11110000000000 h
b0 @
b1111 ]
b0 C
b0 P
b0 S
b0 R
b1111 ^
1(
1N
b0 $
b0 -
b11110000000000 #
b11110000000000 *
b1100000010111000110101001010100011000000101110001101010010101100110000 }
b11010000000000 |
1&
#160000
0&
#165000
b0 :
b0 F
b0 >
b0 ;
b0 e
16
b0 X
b0 U
b0 G
b0 d
b0 A
b0 W
b0 D
1z
b0 s
b0 t
0w
1&
0(
#170000
0&
#175000
0z
b0 x
1!
1&
#180000
0&
#185000
0!
b0 "
b0 g
1&
#190000
0&
#195000
b100001000000000 :
b100001000000000 >
06
08
b10000 G
b1100000000000000000000 F
b10000 d
b1100000000000000000000 ;
b1100000000000000000000 e
b1100000000000000000000 U
b1100000000000000000000 X
b10000 W
0B
b1100000000000000000000 J
b10000 L
b11000000000 I
b10000 M
b1000000000 K
0r
0o
1w
b100001000000000 p
b100000000000000 l
b1011110000000000 h
b10000 C
b10000 R
b100000000000000000000 @
b10000000000 P
15
b10000 S
1Z
1(
b100001000000000 %
b100001000000000 /
0N
b100000000000000 $
b100000000000000 -
b1011110000000000 #
b1011110000000000 *
b11000100101010001100000010101100110000 }
b0 |
1&
#200000
0&
#205000
b11110000000000 :
b11110000000000 >
b1111 G
b1000000000000000000000 F
b1111 d
b1 {
b1 c
b1000000000000000000000 ;
b1000000000000000000000 e
b100000000000000000000 U
b100000000000000000000 X
b1000000000000000000000 A
b10000 D
1z
b100001000000000 x
1v
b10000 s
b100000000000000000000 t
0w
1&
0(
#210000
0&
#215000
0z
b11110000000000 x
1!
b100001000000000 "
b100001000000000 g
1&
#220000
0&
#225000
0!
b11110000000000 "
b11110000000000 g
1&
#230000
0&
#235000
b10000 G
b1100000000000000 >
07
0E
0<
09
b1000000000000000000000 F
b1 c
b10000 d
b1000000000000000000000 ;
b1000000000000000000000 e
1f
b1000000000000000000000 U
1T
12
b1000000000000000000000 X
1B
b0 J
b0 I
b111111000000000 :
1,
b0 L
b0 M
b0 K
1r
1j
1w
b0 p
b11110000000000 l
b111111000000000 h
b110000000000000000000 @
b11111 C
b11000000000 [
b1111 R
b11111 ]
05
b1111 S
0Z
b11111 ^
b1000000000 \
1(
b0 %
b0 /
b11110000000000 $
b11110000000000 -
b111111000000000 #
b111111000000000 *
b1011010011000100101010001100100010101100110011 }
b11110000000000 |
1&
#240000
0&
#245000
b1100000000000000000000 F
b111110000000000 >
b1100000000000000000000 ;
b1100000000000000000000 e
1=
b1100000000000000000000 X
b1100000000000000000000 U
b11111 G
b11111 d
0f
b1100000000000000000000 A
0T
b11111 W
b11111 D
1y
1z
b111111000000000 x
0v
b11111 s
b110000000000000000000 t
0w
1&
0(
#250000
0&
#255000
0y
0z
1!
b111111000000000 "
b111111000000000 g
1&
#260000
0&
#265000
0!
1&
#270000
0&
#275000
1n
0j
1w
b111111000000000 l
b11110000000000 h
b110000000000000000000 @
b11000000000 P
b10000000000 [
b11111 R
b1111 ]
b11111 S
b1000000000 Q
b1111 ^
b0 \
1(
b111111000000000 $
b111111000000000 -
b11110000000000 #
b11110000000000 *
b1001110011000010100111000101010001100010010101100110000 }
b111111000000000 |
1&
#280000
0&
#285000
1z
0w
1&
0(
#290000
0&
#295000
0z
1!
1&
#300000
0&
#305000
0!
1&
#310000
0&
#315000
b100000 G
b1100000000000000000000 F
b100000 d
b1100000000000000000000 ;
b1100000000000000000000 e
b0 X
b11000000000000000000000 U
b1100000000000000000000 J
b11111 L
b11000000000 I
b11111 M
b1000000000 K
0r
1q
0n
1j
1w
b111111000000000 p
b11110000000000 l
b111111000000000 h
b110000000000000000000 @
b10000000000 P
b11000000000 [
b1111 R
b11111 ]
b1111 S
b0 Q
b11111 ^
b1000000000 \
1(
b111111000000000 %
b111111000000000 /
b11110000000000 $
b11110000000000 -
b111111000000000 #
b111111000000000 *
b110001001010100100111001100001010011100010101100110000 }
1&
#320000
0&
#325000
1z
0w
1&
0(
#330000
0&
#335000
0z
1!
1&
#340000
0&
#345000
0!
1&
#350000
0&
#355000
b11111 G
b11111 d
b1100000000000000000000 X
b1100000000000000000000 U
b0 J
b0 I
b111110000000000 :
b0 L
13
0,
b0 M
b0 K
1r
1i
0q
0j
1w
b0 p
b111110000000000 h
b100000000000000000000 @
b10000000000 [
b0 \
1(
b0 %
b0 /
b111110000000000 #
b111110000000000 *
b10011100110000101001110001010100011000100101011010011100110000101001110 }
1&
#360000
0&
#365000
b1000000000000000000000 F
b1000000000000000000000 ;
b1000000000000000000000 e
b1000000000000000000000 X
b1000000000000000000000 U
b1000000000000000000000 A
1z
b111110000000000 x
b100000000000000000000 t
0w
1&
0(
#370000
0&
#375000
0z
1!
b111110000000000 "
b111110000000000 g
1&
#380000
0&
#385000
0!
1&
#390000
0&
#395000
1w
b1111110000000000 h
15
1Z
1(
b1111110000000000 #
b1111110000000000 *
b1001001011011100110011000101010001100010010101100110000 }
b111110000000000 |
1&
#400000
0&
#405000
b1111110000000000 :
1f
1T
1z
1v
0w
1&
0(
#410000
0&
#415000
1y
0z
b1111110000000000 x
1!
1&
#420000
0&
#425000
0!
b1111110000000000 "
b1111110000000000 g
1&
#430000
0&
#435000
b111111000000000 :
14
1o
1w
b0 l
b111110000000000 h
b0 @
b10000 C
b0 P
05
b0 S
b0 R
0Z
1(
1N
b0 $
b0 -
b111110000000000 #
b111110000000000 *
b10110101001001011011100110011000101010001100010010101100110000 }
b1111110000000000 |
1&
#440000
0&
#445000
16
b0 >
b0 F
b0 ;
b0 e
0=
b0 X
b0 U
b0 G
b0 d
0f
b0 A
0T
b10000 W
b10000 D
1z
b111111000000000 x
0v
b10000 s
b0 t
0w
1&
0(
#450000
0&
#455000
0y
0z
1!
b111111000000000 "
b111111000000000 g
1&
#460000
0&
#465000
0!
1&
#470000
0&
