HDL/fp32_fma.v
`timescale 1ns/1ps

// =============================================================================
// fp32_fma — IEEE 754 single-precision Fused Multiply-Add unit
//
// Computes: result = (a * b) + c  in FP32 (binary32) format.
// Pipeline latency: 3 cycles.
//
// IEEE 754 single-precision format:
//   [31]    sign
//   [30:23] exponent (8 bits, bias = 127)
//   [22:0]  mantissa (23 bits, implicit leading 1)
//
// Fixes applied:
//   1. Pipeline: multiply results registered into stage 1
//   2. Underflow: signed norm_exp prevents unsigned wrap
//   3. Rounding: round-to-nearest-even
//   4. Special cases: NaN, Inf, zero*Inf
// =============================================================================

module fp32_fma (
    input  wire        clk,
    input  wire        rst_n,
    input  wire [31:0] a,
    input  wire [31:0] b,
    input  wire [31:0] c,
    input  wire        valid_in,
    output reg  [31:0] result,
    output reg         valid_out
);

    localparam FP32_BIAS = 127;
    localparam FP32_ZERO = 32'h00000000;
    localparam FP32_INF  = 32'h7F800000;
    localparam FP32_NAN  = 32'h7FC00000;

    // =========================================================================
    // Pipeline stage 1
    // =========================================================================
    reg [31:0] s1_a, s1_b, s1_c;
    reg        s1_valid;

    reg s1_a_nan, s1_b_nan, s1_c_nan;
    reg s1_a_inf, s1_b_inf, s1_c_inf;
    reg s1_a_zero, s1_b_zero, s1_c_zero;

    reg [47:0] s1_mul_man;
    reg [8:0]  s1_mul_exp;
    reg        s1_mul_sign;
    reg        s1_mul_overflow;

    // Unpack a
    wire        a_sign_w = a[31];
    wire [7:0]  a_exp_w  = a[30:23];
    wire [22:0] a_man_w  = a[22:0];
    wire        a_zero_w = (a[30:0] == 31'h00000000);
    wire        a_den_w  = (a_exp_w == 0) && (a_man_w != 0);

    wire [23:0] a_mantissa_w;
    assign a_mantissa_w[23]   = (a_zero_w || a_den_w) ? 1'b0 : 1'b1;
    assign a_mantissa_w[22:0] = a_zero_w ? 23'd0 : (a_den_w ? {1'b0, a_man_w} : a_man_w);
    wire [8:0]  a_exponent_w = a_zero_w ? 9'd0 : (a_den_w ? 9'd1 : {1'b0, a_exp_w});

    // Unpack b
    wire        b_sign_w = b[31];
    wire [7:0]  b_exp_w  = b[30:23];
    wire [22:0] b_man_w  = b[22:0];
    wire        b_zero_w = (b[30:0] == 31'h00000000);
    wire        b_den_w  = (b_exp_w == 0) && (b_man_w != 0);

    wire [23:0] b_mantissa_w;
    assign b_mantissa_w[23]   = (b_zero_w || b_den_w) ? 1'b0 : 1'b1;
    assign b_mantissa_w[22:0] = b_zero_w ? 23'd0 : (b_den_w ? {1'b0, b_man_w} : b_man_w);
    wire [8:0]  b_exponent_w = b_zero_w ? 9'd0 : (b_den_w ? 9'd1 : {1'b0, b_exp_w});

    // Multiply
    wire        mul_sign_w = a_sign_w ^ b_sign_w;
    wire [8:0]  mul_exp_w  = a_exponent_w + b_exponent_w - FP32_BIAS;
    wire [47:0] mul_man_w  = a_mantissa_w * b_mantissa_w;
    wire        mul_ovf_w  = mul_man_w[47];

    always @(posedge clk or negedge rst_n) begin
        if (!rst_n) begin
            s1_a <= 0; s1_b <= 0; s1_c <= 0;
            s1_valid <= 0;
            s1_a_nan <= 0; s1_b_nan <= 0; s1_c_nan <= 0;
            s1_a_inf <= 0; s1_b_inf <= 0; s1_c_inf <= 0;
            s1_a_zero <= 0; s1_b_zero <= 0; s1_c_zero <= 0;
            s1_mul_man <= 0; s1_mul_exp <= 0;
            s1_mul_sign <= 0; s1_mul_overflow <= 0;
        end else begin
            s1_a <= a; s1_b <= b; s1_c <= c;
            s1_valid <= valid_in;
            s1_a_nan   <= (a[30:23] == 8'd255) && (a[22:0] != 23'd0);
            s1_b_nan   <= (b[30:23] == 8'd255) && (b[22:0] != 23'd0);
            s1_c_nan   <= (c[30:23] == 8'd255) && (c[22:0] != 23'd0);
            s1_a_inf   <= (a[30:23] == 8'd255) && (a[22:0] == 23'd0);
            s1_b_inf   <= (b[30:23] == 8'd255) && (b[22:0] == 23'd0);
            s1_c_inf   <= (c[30:23] == 8'd255) && (c[22:0] == 23'd0);
            s1_a_zero  <= (a[30:0] == 31'h00000000);
            s1_b_zero  <= (b[30:0] == 31'h00000000);
            s1_c_zero  <= (c[30:0] == 31'h00000000);
            s1_mul_man      <= mul_man_w;
            s1_mul_exp      <= mul_exp_w;
            s1_mul_sign     <= mul_sign_w;
            s1_mul_overflow <= mul_ovf_w;
        end
    end

    // =========================================================================
    // Pipeline stage 2
    // =========================================================================

    // Unpack s1_c
    wire        c_sign = s1_c[31];
    wire [7:0]  c_exp  = s1_c[30:23];
    wire [22:0] c_man  = s1_c[22:0];
    wire        c_den  = (c_exp == 0) && (c_man != 0);

    wire [23:0] c_mantissa;
    assign c_mantissa[23]   = (s1_c_zero || c_den) ? 1'b0 : 1'b1;
    assign c_mantissa[22:0] = s1_c_zero ? 23'd0 : (c_den ? {1'b0, c_man} : c_man);
    wire [8:0]  c_exponent = s1_c_zero ? 9'd0 : (c_den ? 9'd1 : {1'b0, c_exp});

    wire [8:0]  mul_exp_eff = s1_mul_overflow ? (s1_mul_exp + 9'd1) : s1_mul_exp;
    wire [8:0]  add_exp = (mul_exp_eff > c_exponent) ? mul_exp_eff : c_exponent;

    // Align mantissas: implicit 1 at bit 47
    wire [47:0] mul_man_aligned = (mul_exp_eff >= c_exponent) ?
        (s1_mul_man << 1) :
        (s1_mul_man << 1) >> (c_exponent - mul_exp_eff);
    wire [47:0] c_man_aligned = (c_exponent > mul_exp_eff) ?
        ({c_mantissa, 24'd0}) :
        ({c_mantissa, 24'd0} >> (mul_exp_eff - c_exponent));

    // Add
    wire        mul_ge_c = (mul_man_aligned >= c_man_aligned);
    wire [48:0] abs_diff = mul_ge_c ?
        ({1'b0, mul_man_aligned} - {1'b0, c_man_aligned}) :
        ({1'b0, c_man_aligned} - {1'b0, mul_man_aligned});

    wire        add_sign = (s1_mul_sign == c_sign) ? s1_mul_sign :
                           mul_ge_c ? s1_mul_sign : c_sign;
    wire [48:0] add_result = (s1_mul_sign == c_sign) ?
        ({1'b0, mul_man_aligned} + {1'b0, c_man_aligned}) :
        abs_diff;

    // Normalize
    reg [47:0] norm_man;
    reg signed [9:0] norm_exp;
    reg        norm_sign;
    reg [5:0]  lead_pos;
    integer shift;

    always @(*) begin
        norm_sign = add_sign;
        if (add_result == 0) begin
            norm_man = 0;
            norm_exp = 0;
        end else if (add_result[48]) begin
            norm_man = add_result[48:1];
            norm_exp = {1'b0, add_exp} + 10'd1;
        end else begin
            norm_man = add_result[47:0];
            norm_exp = {1'b0, add_exp};
            if (!norm_man[47]) begin
                lead_pos = 0;
                if      (norm_man[46]) lead_pos = 1;
                else if (norm_man[45]) lead_pos = 2;
                else if (norm_man[44]) lead_pos = 3;
                else if (norm_man[43]) lead_pos = 4;
                else if (norm_man[42]) lead_pos = 5;
                else if (norm_man[41]) lead_pos = 6;
                else if (norm_man[40]) lead_pos = 7;
                else if (norm_man[39]) lead_pos = 8;
                else if (norm_man[38]) lead_pos = 9;
                else if (norm_man[37]) lead_pos = 10;
                else if (norm_man[36]) lead_pos = 11;
                else if (norm_man[35]) lead_pos = 12;
                else if (norm_man[34]) lead_pos = 13;
                else if (norm_man[33]) lead_pos = 14;
                else if (norm_man[32]) lead_pos = 15;
                else if (norm_man[31]) lead_pos = 16;
                else if (norm_man[30]) lead_pos = 17;
                else if (norm_man[29]) lead_pos = 18;
                else if (norm_man[28]) lead_pos = 19;
                else if (norm_man[27]) lead_pos = 20;
                else if (norm_man[26]) lead_pos = 21;
                else if (norm_man[25]) lead_pos = 22;
                else if (norm_man[24]) lead_pos = 23;
                else if (norm_man[23]) lead_pos = 24;
                else if (norm_man[22]) lead_pos = 25;
                else if (norm_man[21]) lead_pos = 26;
                else if (norm_man[20]) lead_pos = 27;
                else if (norm_man[19]) lead_pos = 28;
                else if (norm_man[18]) lead_pos = 29;
                else if (norm_man[17]) lead_pos = 30;
                else if (norm_man[16]) lead_pos = 31;
                else if (norm_man[15]) lead_pos = 32;
                else if (norm_man[14]) lead_pos = 33;
                else if (norm_man[13]) lead_pos = 34;
                else if (norm_man[12]) lead_pos = 35;
                else if (norm_man[11]) lead_pos = 36;
                else if (norm_man[10]) lead_pos = 37;
                else if (norm_man[9])  lead_pos = 38;
                else if (norm_man[8])  lead_pos = 39;
                else if (norm_man[7])  lead_pos = 40;
                else if (norm_man[6])  lead_pos = 41;
                else if (norm_man[5])  lead_pos = 42;
                else if (norm_man[4])  lead_pos = 43;
                else if (norm_man[3])  lead_pos = 44;
                else if (norm_man[2])  lead_pos = 45;
                else if (norm_man[1])  lead_pos = 46;
                else                   lead_pos = 47;
                shift = lead_pos;
                norm_man = norm_man << shift;
                norm_exp = norm_exp - shift;
            end
        end
    end

    // Round-to-nearest-even
    // Mantissa field: norm_man[46:24] (23 bits)
    // Guard: [23], Round: [22], Sticky: |[21:0]
    wire guard  = norm_man[23];
    wire round  = norm_man[22];
    wire sticky = |norm_man[21:0];
    wire round_up = guard & (round | sticky | norm_man[24]);

    wire [47:0] rounded_man = norm_man + (round_up ? 48'h000000000800 : 48'd0);  // add 1 at bit 23
    wire rounded_carry = ~rounded_man[47] & norm_man[47];

    wire [47:0] final_man = rounded_carry ? 48'h008000000000 : rounded_man;  // 1<<47
    wire [9:0]  final_exp = rounded_carry ? (norm_exp + 10'd1) : norm_exp;

    // Pack result
    wire result_underflow = (norm_exp < 0) || (norm_exp == 0 && !rounded_carry);
    wire result_overflow  = (final_exp >= 255);
    wire [31:0] packed_result;
    assign packed_result = result_underflow ? (norm_sign ? 32'h80000000 : FP32_ZERO) :
                           result_overflow  ? {norm_sign, 8'd255, 23'd0} :
                           {norm_sign, final_exp[7:0], final_man[46:24]};

    // Special cases
    wire any_nan = s1_a_nan | s1_b_nan | s1_c_nan;
    wire mul_inf_zero = (s1_a_inf & s1_b_zero) | (s1_b_inf & s1_a_zero);
    wire mul_inf = s1_a_inf | s1_b_inf;
    wire add_inf = s1_c_inf;
    wire inf_add_nan = mul_inf & add_inf & (s1_mul_sign != c_sign);

    wire is_special = any_nan | mul_inf_zero | mul_inf | add_inf;

    wire [31:0] special_result =
        any_nan      ? FP32_NAN :
        mul_inf_zero ? FP32_NAN :
        inf_add_nan  ? FP32_NAN :
        mul_inf      ? {s1_mul_sign, 8'd255, 23'd0} :
        add_inf      ? s1_c :
                       packed_result;

    reg [31:0] s2_result;
    reg        s2_valid;

    always @(posedge clk or negedge rst_n) begin
        if (!rst_n) begin
            s2_result <= 0;
            s2_valid  <= 0;
        end else begin
            s2_result <= is_special ? special_result : packed_result;
            s2_valid  <= s1_valid;
        end
    end

    // Stage 3
    always @(posedge clk or negedge rst_n) begin
        if (!rst_n) begin
            result    <= 0;
            valid_out <= 0;
        end else begin
            result    <= s2_result;
            valid_out <= s2_valid;
        end
    end

endmodule

HDL/tb_fp32_fma.v
`timescale 1ns/1ps

// =============================================================================
// tb_fp32_fma — self-checking testbench for FP32 FMA unit
// =============================================================================
module tb_fp32_fma;

    reg         clk = 0;
    reg         rst_n = 0;
    reg  [31:0] a, b, c;
    reg         valid_in;
    wire [31:0] result;
    wire        valid_out;

    always #5 clk = ~clk;

    fp32_fma dut (
        .clk(clk), .rst_n(rst_n),
        .a(a), .b(b), .c(c), .valid_in(valid_in),
        .result(result), .valid_out(valid_out)
    );

    integer errors;

    task check;
        input [31:0] exp;
        input [8*32-1:0] name;
        begin
            if (result !== exp) begin
                $display("[TB] MISMATCH (%0s): a=%h b=%h c=%h -> got %h, expected %h", name, a, b, c, result, exp);
                errors = errors + 1;
            end
        end
    endtask

    task run_op;
        begin
            valid_in = 1; #10; valid_in = 0;
            repeat (4) @(posedge clk);
        end
    endtask

    initial begin
        $dumpfile("tb_fp32_fma.vcd");
        $dumpvars(0, tb_fp32_fma);
        errors = 0;

        #25; rst_n = 1; #10;

        // Test 1: 1.0 * 1.0 + 0.0 = 1.0
        a = 32'h3F800000; b = 32'h3F800000; c = 32'h00000000;
        run_op; check(32'h3F800000, "1*1+0");

        // Test 2: 2.0 * 3.0 + 1.0 = 7.0
        a = 32'h40000000; b = 32'h40400000; c = 32'h3F800000;
        run_op; check(32'h40E00000, "2*3+1");

        // Test 3: 0.5 * 0.5 + 0.0 = 0.25
        a = 32'h3F000000; b = 32'h3F000000; c = 32'h00000000;
        run_op; check(32'h3E800000, "0.5*0.5+0");

        // Test 4: 1.0 * 0.0 + 0.0 = 0.0
        a = 32'h3F800000; b = 32'h00000000; c = 32'h00000000;
        run_op; check(32'h00000000, "1*0+0");

        // Test 5: -1.0 * 2.0 + 3.0 = 1.0
        a = 32'hBF800000; b = 32'h40000000; c = 32'h40400000;
        run_op; check(32'h3F800000, "-1*2+3");

        // Test 6: NaN * 1 = NaN
        a = 32'h7FC00000; b = 32'h3F800000; c = 32'h00000000;
        run_op; check(32'h7FC00000, "NaN*1");

        // Test 7: Inf * 0 = NaN
        a = 32'h7F800000; b = 32'h00000000; c = 32'h00000000;
        run_op; check(32'h7FC00000, "Inf*0");

        // Test 8: Inf + (-Inf) = NaN
        a = 32'h7F800000; b = 32'h3F800000; c = 32'hFF800000;
        run_op; check(32'h7FC00000, "Inf+(-Inf)");

        if (errors == 0)
            $display("*** FP32 FMA TEST PASSED ***");
        else
            $display("*** FP32 FMA TEST FAILED (%0d errors) ***", errors);

        $finish;
    end

    initial begin #10000; $display("TIMEOUT"); $finish(1); end

endmodule

HDL/tb_fp32_fma.vcd
$date
	Wed Aug 19 07:53:51 2026
$end
$version
	Icarus Verilog
$end
$timescale
	1ps
$end
$scope module tb_fp32_fma $end
$var wire 1 ! valid_out $end
$var wire 32 " result [31:0] $end
$var reg 32 # a [31:0] $end
$var reg 32 $ b [31:0] $end
$var reg 32 % c [31:0] $end
$var reg 1 & clk $end
$var reg 1 ' rst_n $end
$var reg 1 ( valid_in $end
$var integer 32 ) errors [31:0] $end
$scope module dut $end
$var wire 32 * a [31:0] $end
$var wire 1 + a_den_w $end
$var wire 1 , any_nan $end
$var wire 32 - b [31:0] $end
$var wire 1 . b_den_w $end
$var wire 32 / c [31:0] $end
$var wire 1 0 c_den $end
$var wire 1 & clk $end
$var wire 1 1 inf_add_nan $end
$var wire 1 2 is_special $end
$var wire 1 3 mul_inf $end
$var wire 1 4 mul_inf_zero $end
$var wire 1 5 mul_sign_w $end
$var wire 1 6 result_underflow $end
$var wire 1 7 round_up $end
$var wire 1 8 rounded_carry $end
$var wire 1 ' rst_n $end
$var wire 1 ( valid_in $end
$var wire 1 9 sticky $end
$var wire 32 : special_result [31:0] $end
$var wire 48 ; rounded_man [47:0] $end
$var wire 1 < round $end
$var wire 1 = result_overflow $end
$var wire 32 > packed_result [31:0] $end
$var wire 1 ? mul_ovf_w $end
$var wire 48 @ mul_man_w [47:0] $end
$var wire 48 A mul_man_aligned [47:0] $end
$var wire 1 B mul_ge_c $end
$var wire 9 C mul_exp_w [8:0] $end
$var wire 9 D mul_exp_eff [8:0] $end
$var wire 1 E guard $end
$var wire 48 F final_man [47:0] $end
$var wire 10 G final_exp [9:0] $end
$var wire 1 H c_sign $end
$var wire 24 I c_mantissa [23:0] $end
$var wire 48 J c_man_aligned [47:0] $end
$var wire 23 K c_man [22:0] $end
$var wire 9 L c_exponent [8:0] $end
$var wire 8 M c_exp [7:0] $end
$var wire 1 N b_zero_w $end
$var wire 1 O b_sign_w $end
$var wire 24 P b_mantissa_w [23:0] $end
$var wire 23 Q b_man_w [22:0] $end
$var wire 9 R b_exponent_w [8:0] $end
$var wire 8 S b_exp_w [7:0] $end
$var wire 1 T add_sign $end
$var wire 49 U add_result [48:0] $end
$var wire 1 V add_inf $end
$var wire 9 W add_exp [8:0] $end
$var wire 49 X abs_diff [48:0] $end
$var wire 1 Y a_zero_w $end
$var wire 1 Z a_sign_w $end
$var wire 24 [ a_mantissa_w [23:0] $end
$var wire 23 \ a_man_w [22:0] $end
$var wire 9 ] a_exponent_w [8:0] $end
$var wire 8 ^ a_exp_w [7:0] $end
$var parameter 32 _ FP32_BIAS $end
$var parameter 32 ` FP32_INF $end
$var parameter 32 a FP32_NAN $end
$var parameter 32 b FP32_ZERO $end
$var reg 6 c lead_pos [5:0] $end
$var reg 10 d norm_exp [9:0] $end
$var reg 48 e norm_man [47:0] $end
$var reg 1 f norm_sign $end
$var reg 32 g result [31:0] $end
$var reg 32 h s1_a [31:0] $end
$var reg 1 i s1_a_inf $end
$var reg 1 j s1_a_nan $end
$var reg 1 k s1_a_zero $end
$var reg 32 l s1_b [31:0] $end
$var reg 1 m s1_b_inf $end
$var reg 1 n s1_b_nan $end
$var reg 1 o s1_b_zero $end
$var reg 32 p s1_c [31:0] $end
$var reg 1 V s1_c_inf $end
$var reg 1 q s1_c_nan $end
$var reg 1 r s1_c_zero $end
$var reg 9 s s1_mul_exp [8:0] $end
$var reg 48 t s1_mul_man [47:0] $end
$var reg 1 u s1_mul_overflow $end
$var reg 1 v s1_mul_sign $end
$var reg 1 w s1_valid $end
$var reg 32 x s2_result [31:0] $end
$var reg 1 y s2_valid $end
$var reg 1 ! valid_out $end
$var integer 32 z shift [31:0] $end
$upscope $end
$scope task check $end
$var reg 32 { exp [31:0] $end
$var reg 256 | name [255:0] $end
$upscope $end
$scope task run_op $end
$upscope $end
$upscope $end
$enddefinitions $end
$comment Show the parameter values. $end
$dumpall
b0 b
b1111111110000000000000000000000 a
b1111111100000000000000000000000 `
b1111111 _
$end
#0
$dumpvars
bx |
bx {
bx z
0y
b0 x
0w
0v
0u
b0 t
b0 s
0r
0q
b0 p
0o
0n
0m
b0 l
0k
0j
0i
b0 h
b0 g
0f
b100000000000000000000000000000000000000000000000 e
b0 d
bx c
bx ^
b0xxxxxxxx ]
bx \
bx [
xZ
xY
b100000000000000000000000000000000000000000000000 X
b0 W
0V
b100000000000000000000000000000000000000000000000 U
0T
bx S
b0xxxxxxxx R
bx Q
bx P
xO
xN
b0 M
b0 L
b0 K
b100000000000000000000000000000000000000000000000 J
b100000000000000000000000 I
0H
b0 G
b100000000000000000000000000000000000000000000000 F
0E
b0 D
bx C
0B
b0 A
bx @
x?
b0 >
0=
0<
b100000000000000000000000000000000000000000000000 ;
b0 :
09
08
07
16
x5
04
03
02
01
00
bx /
x.
bx -
0,
x+
bx *
b0 )
x(
0'
0&
bx %
bx $
bx #
b0 "
0!
$end
#5000
1&
#10000
0&
#15000
1&
#20000
0&
#25000
x8
x7
xE
x<
x9
bx F
bx ;
bx e
x=
bx >
bx U
b0xxxxxxxx L
bx G
x6
bx X
bx I
x0
b0xxxxxxxxx d
xf
bx W
bx A
xB
bx J
x1
x4
bx :
xT
bx D
x2
x3
x,
xH
bx M
bx K
xu
xv
bx s
bx t
xr
xo
xk
xV
xm
xi
xq
xn
xj
xw
bx p
bx l
bx h
1&
1'
#30000
0&
#35000
02
b0 I
00
01
04
b0 L
03
0,
0H
b0 M
b0 K
1r
0o
0k
0V
0m
0i
0q
0n
0j
1w
b0 p
b111111100000000000000000000000 l
b111111100000000000000000000000 h
xy
bx x
0?
b10000000000000000000000000000000000000000000000 @
b1111111 C
b100000000000000000000000 P
b100000000000000000000000 [
b1111111 R
b1111111 ]
0.
0+
05
0O
b1111111 S
b0 Q
0N
0Z
b1111111 ^
b0 \
0Y
1&
1(
b0 %
b0 /
b111111100000000000000000000000 $
b111111100000000000000000000000 -
b111111100000000000000000000000 #
b111111100000000000000000000000 *
#40000
0&
#45000
0=
08
b111111100000000000000000000000 :
b100000000000000000000000000000000000000000000000 F
b100000000000000000000000000000000000000000000000 ;
07
0E
0<
09
b100000000000000000000000000000000000000000000000 e
b111111100000000000000000000000 >
b100000000000000000000000000000000000000000000000 U
b1111111 G
06
b100000000000000000000000000000000000000000000000 X
b1111111 d
0f
b1111111 W
1B
b100000000000000000000000000000000000000000000000 A
b0 J
0T
b1111111 D
x!
bx "
bx g
1y
0u
0v
b1111111 s
b10000000000000000000000000000000000000000000000 t
0w
1&
0(
#50000
0&
#55000
0y
b111111100000000000000000000000 x
1!
1&
#60000
0&
#65000
0!
b111111100000000000000000000000 "
b111111100000000000000000000000 g
1&
#70000
0&
#75000
b1000000000000000000000000000000 :
b1000000000000000000000000000000 >
b10000000 G
b10000000 d
b0 X
b1000000000000000000000000000000000000000000000000 U
b100000000000000000000000000000000000000000000000 J
b1111111 L
b100000000000000000000000 I
b1111111 M
0r
1w
b111111100000000000000000000000 p
b1000000010000000000000000000000 l
b1000000000000000000000000000000 h
b11000000000000000000000000000000000000000000000 @
b110000000000000000000000 P
b10000001 C
b10000000 R
b10000000 ]
b10000000 S
b10000000000000000000000 Q
b10000000 ^
1(
b111111100000000000000000000000 %
b111111100000000000000000000000 /
b1000000010000000000000000000000 $
b1000000010000000000000000000000 -
b1000000000000000000000000000000 #
b1000000000000000000000000000000 *
b11000100101010001100010010101100110000 |
b111111100000000000000000000000 {
1&
#80000
0&
#85000
b1000000111000000000000000000000 :
b1000000111000000000000000000000 >
b111000000000000000000000000000000000000000000000 F
b111000000000000000000000000000000000000000000000 ;
b111000000000000000000000000000000000000000000000 e
b10000001 G
b101000000000000000000000000000000000000000000000 X
b111000000000000000000000000000000000000000000000 U
b10000001 d
b110000000000000000000000000000000000000000000000 A
b10000001 W
b1000000000000000000000000000000000000000000000 J
b10000001 D
1y
b1000000000000000000000000000000 x
b10000001 s
b11000000000000000000000000000000000000000000000 t
0w
1&
0(
#90000
0&
#95000
0y
b1000000111000000000000000000000 x
1!
b1000000000000000000000000000000 "
b1000000000000000000000000000000 g
1&
#100000
0&
#105000
0!
b1000000111000000000000000000000 "
b1000000111000000000000000000000 g
1&
#110000
0&
#115000
b1000000110000000000000000000000 :
b1000000110000000000000000000000 >
b110000000000000000000000000000000000000000000000 F
b110000000000000000000000000000000000000000000000 ;
b110000000000000000000000000000000000000000000000 e
b110000000000000000000000000000000000000000000000 X
b110000000000000000000000000000000000000000000000 U
b0 I
b0 J
b0 L
b0 M
1r
1w
b0 p
b111111000000000000000000000000 l
b111111000000000000000000000000 h
b10000000000000000000000000000000000000000000000 @
b100000000000000000000000 P
b1111101 C
b1111110 R
b1111110 ]
b1111110 S
b0 Q
b1111110 ^
1(
b0 %
b0 /
b111111000000000000000000000000 $
b111111000000000000000000000000 -
b111111000000000000000000000000 #
b111111000000000000000000000000 *
b11001000101010001100110010101100110001 |
b1000000111000000000000000000000 {
1&
#120000
0&
#125000
b111110100000000000000000000000 :
b111110100000000000000000000000 >
b100000000000000000000000000000000000000000000000 F
b100000000000000000000000000000000000000000000000 ;
b100000000000000000000000000000000000000000000000 e
b100000000000000000000000000000000000000000000000 X
b100000000000000000000000000000000000000000000000 U
b1111101 G
b1111101 d
b100000000000000000000000000000000000000000000000 A
b1111101 W
b1111101 D
1y
b1000000110000000000000000000000 x
b1111101 s
b10000000000000000000000000000000000000000000000 t
0w
1&
0(
#130000
0&
#135000
0y
b111110100000000000000000000000 x
1!
b1000000110000000000000000000000 "
b1000000110000000000000000000000 g
1&
#140000
0&
#145000
0!
b111110100000000000000000000000 "
b111110100000000000000000000000 g
1&
#150000
0&
#155000
1o
1w
b0 l
b111111100000000000000000000000 h
b0 @
b0 C
b0 P
b1111111 ]
b0 R
b0 S
1N
b1111111 ^
1(
b0 $
b0 -
b111111100000000000000000000000 #
b111111100000000000000000000000 *
b1100000010111000110101001010100011000000101110001101010010101100110000 |
b111110100000000000000000000000 {
1&
#160000
0&
#165000
b0 :
b0 F
b0 >
b0 ;
b0 e
16
b0 X
b0 U
b0 G
b0 d
b0 A
b0 W
b0 D
1y
b0 s
b0 t
0w
1&
0(
#170000
0&
#175000
0y
b0 x
1!
1&
#180000
0&
#185000
0!
b0 "
b0 g
1&
#190000
0&
#195000
b1000000010000000000000000000000 :
b1000000010000000000000000000000 >
06
08
b10000000 G
b110000000000000000000000000000000000000000000000 F
b10000000 d
b110000000000000000000000000000000000000000000000 ;
b110000000000000000000000000000000000000000000000 e
b110000000000000000000000000000000000000000000000 U
b110000000000000000000000000000000000000000000000 X
b10000000 W
0B
b110000000000000000000000000000000000000000000000 J
b10000000 L
b110000000000000000000000 I
b10000000 M
b10000000000000000000000 K
0r
0o
1w
b1000000010000000000000000000000 p
b1000000000000000000000000000000 l
b10111111100000000000000000000000 h
b10000000 C
b10000000000000000000000000000000000000000000000 @
b10000000 R
b100000000000000000000000 P
15
b10000000 S
0N
1Z
1(
b1000000010000000000000000000000 %
b1000000010000000000000000000000 /
b1000000000000000000000000000000 $
b1000000000000000000000000000000 -
b10111111100000000000000000000000 #
b10111111100000000000000000000000 *
b11000100101010001100000010101100110000 |
b0 {
1&
#200000
0&
#205000
b111111100000000000000000000000 :
b111111100000000000000000000000 >
b1111111 G
b100000000000000000000000000000000000000000000000 F
b1111111 d
b1 z
b1 c
b100000000000000000000000000000000000000000000000 ;
b100000000000000000000000000000000000000000000000 e
b10000000000000000000000000000000000000000000000 U
b10000000000000000000000000000000000000000000000 X
b100000000000000000000000000000000000000000000000 A
b10000000 D
1y
b1000000010000000000000000000000 x
1v
b10000000 s
b10000000000000000000000000000000000000000000000 t
0w
1&
0(
#210000
0&
#215000
0y
b111111100000000000000000000000 x
1!
b1000000010000000000000000000000 "
b1000000010000000000000000000000 g
1&
#220000
0&
#225000
0!
b111111100000000000000000000000 "
b111111100000000000000000000000 g
1&
#230000
0&
#235000
b11000000000000000000000000000000 >
b10000000 G
b10000000 d
1f
12
b100000000000000000000000000000000000000000000000 U
1T
b100000000000000000000000000000000000000000000000 X
b0 I
b1111111110000000000000000000000 :
1B
b0 J
1,
b0 L
b0 M
b0 K
1r
1j
1w
b0 p
b111111100000000000000000000000 l
b1111111110000000000000000000000 h
b11000000000000000000000000000000000000000000000 @
b11111111 C
b110000000000000000000000 [
b1111111 R
b11111111 ]
05
b1111111 S
0Z
b11111111 ^
b10000000000000000000000 \
1(
b0 %
b0 /
b111111100000000000000000000000 $
b111111100000000000000000000000 -
b1111111110000000000000000000000 #
b1111111110000000000000000000000 *
b1011010011000100101010001100100010101100110011 |
b111111100000000000000000000000 {
1&
#240000
0&
#245000
b110000000000000000000000000000000000000000000000 F
b1111111100000000000000000000000 >
b110000000000000000000000000000000000000000000000 ;
b110000000000000000000000000000000000000000000000 e
1=
b110000000000000000000000000000000000000000000000 X
b110000000000000000000000000000000000000000000000 U
b11111111 G
b11111111 d
0f
b110000000000000000000000000000000000000000000000 A
0T
b11111111 W
b11111111 D
1y
b1111111110000000000000000000000 x
0v
b11111111 s
b11000000000000000000000000000000000000000000000 t
0w
1&
0(
#250000
0&
#255000
0y
1!
b1111111110000000000000000000000 "
b1111111110000000000000000000000 g
1&
#260000
0&
#265000
0!
1&
#270000
0&
#275000
b1111111110000000000000000000000 :
14
0,
13
1o
1i
0j
1w
b0 l
b1111111100000000000000000000000 h
b100000000000000000000000 [
b0 @
b10000000 C
b0 P
b0 R
b0 S
1N
b0 \
1(
b0 $
b0 -
b1111111100000000000000000000000 #
b1111111100000000000000000000000 *
b100111001100001010011100010101000110001 |
b1111111110000000000000000000000 {
1&
#280000
0&
#285000
16
b0 >
b0 F
b0 ;
b0 e
0=
b0 X
b0 U
b0 G
b0 d
b0 A
b10000000 W
b10000000 D
1y
b10000000 s
b0 t
0w
1&
0(
#290000
0&
#295000
0y
1!
1&
#300000
0&
#305000
0!
1&
#310000
0&
#315000
1=
06
08
b11111111100000000000000000000000 >
b11111111 G
b100000000000000000000000000000000000000000000000 F
b11111111 d
b100000000000000000000000000000000000000000000000 ;
b100000000000000000000000000000000000000000000000 e
1f
b100000000000000000000000000000000000000000000000 U
1T
b100000000000000000000000000000000000000000000000 X
b11111111 W
0B
b100000000000000000000000000000000000000000000000 J
b11111111 L
b100000000000000000000000 I
04
11
1H
b11111111 M
0r
0o
1V
1w
b11111111100000000000000000000000 p
b111111100000000000000000000000 l
b11111111 C
b10000000000000000000000000000000000000000000000 @
b1111111 R
b100000000000000000000000 P
b1111111 S
0N
1(
b11111111100000000000000000000000 %
b11111111100000000000000000000000 /
b111111100000000000000000000000 $
b111111100000000000000000000000 -
b100100101101110011001100010101000110000 |
1&
#320000
0&
#325000
b0 >
0=
16
b0 G
b0 F
b0 d
b0 ;
b0 e
0f
b0 U
0T
b0 X
1B
b100000000000000000000000000000000000000000000000 A
b11111111 D
1y
b11111111 s
b10000000000000000000000000000000000000000000000 t
0w
1&
0(
#330000
0&
#335000
0y
1!
1&
#340000
0&
#345000
0!
1&
#350000
0&
#355000
b1001001011011100110011000101011001010000010110101001001011011100110011000101001 |
1&
